Workbook

Sheet Portada
A1: ESPECIFICACIÓN DE REQUERIMIENTOS DE SOFTWARE (SRS)
A2: Plataforma de componentes transversales (TR)
A3: Conjunto de servicios, librerías y aplicaciones compartidas sobre los que se construyen los nueve productos (SazónPOS, PsicoAgenda, TurnoFácil, LibroPOS, GymControl, ClínicaNet, DocuFlujo, MercaWeb y JurisFlujo). Provee la estructura organizacional multi-tenant, la seguridad con permisos por alcance, catálogos, parámetros, correlativos, personas, identidad DNI/RUC, facturación electrónica, pagos, notificaciones, archivos, auditoría, eventos de dominio, reportes, IA, observabilidad, centro de soporte, gestor de contenidos web, portal del cliente final, integración externa y el agente local (edge). Se implementa como módulos NestJS 11 del monolito modular (hexagonal), librerías Angular 19 del monorepo Nx, esquemas PostgreSQL (Supabase) con RLS por tenant, Redis/BullMQ y Socket.IO.
A5: Versión | B5: 1.0 — Base para el SDD
A6: Fecha | B6: 10 de octubre de 2026
A7: Autor | B7: Israel Lozano (IsLozanDev) — Arquitectura y desarrollo
A8: Stack | B8: Backend NestJS 11 (monolito modular, hexagonal) · Frontend Angular 19 en monorepo Nx · PostgreSQL (Supabase) con RLS · Redis/BullMQ
A9: Documentos relacionados | B9: Definición de Producto y Arquitectura v1.2 · Componentes Transversales · Guía de Arquitectura de Código Backend · Plataforma de Operación
A11: Resumen
A12: Aplicaciones (frontends Nx) | B12: =COUNTA(Aplicaciones!A:A)-3 -> 5
A13: Módulos | B13: =COUNTA(Módulos!A:A)-3 -> 21
A14: Actores | B14: =COUNTA(Actores!A:A)-3 -> 18
A15: Procesos de negocio | B15: =COUNTA(Procesos!A:A)-3 -> 13
A16: Reglas de negocio | B16: =COUNTA('Reglas de negocio'!A:A)-3 -> 48
A17: Requerimientos funcionales (RF) | B17: =COUNTA(RF!A:A)-3 -> 138
A18: RF prioridad Must | B18: =COUNTIF(RF!M:M,"Must") -> 97
A19: RF de la fase MVP | B19: =COUNTIF(RF!N:N,"MVP") -> 110
A20: Criterios de aceptación (GWT) | B20: =COUNTA('Criterios GWT'!A:A)-3 -> 338
A21: RNF propios del sistema | B21: =COUNTIF(RNF!B:B,"Propio") -> 28
A22: RNF heredados de la plataforma | B22: =COUNTIF(RNF!B:B,"Plataforma") -> 30
A23: Componentes transversales utilizados | B23: =COUNTIF(Componentes!C:C,"<>")-1 -> 21
A25: Contenido del libro
A26: Aplicaciones | B26: Frontends Angular del sistema (apps del monorepo Nx), tipo, usuarios
A27: Módulos | B27: Módulos funcionales y la aplicación donde viven
A28: Actores | B28: Actores internos, externos y sistemas externos
A29: Procesos | B29: Procesos de negocio con disparador, pasos y resultado
A30: Reglas de negocio | B30: Reglas de negocio, cálculo, validación y normativas
A31: RF | B31: Requerimientos funcionales de bajo nivel: flujo, datos, permisos, reglas, trazas
A32: Criterios GWT | B32: Criterios de aceptación atómicos DADO QUE / CUANDO / ENTONCES, con estado de prueba
A33: RNF | B33: Requerimientos no funcionales (ISO/IEC 25010:2023): propios y heredados de la plataforma
A34: Matriz Proceso-RF | B34: Trazabilidad procesos × requerimientos funcionales
A35: Matriz RF-RNF | B35: Trazabilidad requerimientos funcionales × no funcionales
A36: Trazabilidad | B36: Vista plana proceso → RF → RNF → criterios → componentes (para importar al SDD)
A37: Componentes | B37: Matriz de componentes transversales y núcleos que el sistema usa, integra o extiende
A38: Consumidores | B38: Matriz componente × sistema consumidor
A40: Convenciones
A41: Prioridad (MoSCoW) | B41: Must = imprescindible para salir · Should = importante · Could = deseable · Won't = fuera de esta versión
A42: Fase | B42: MVP = primera versión vendible · R2 = segunda entrega · R3 = tercera entrega
A43: Tipo de criterio | B43: Positivo = camino feliz · Negativo = entrada inválida o regla incumplida · Borde = límite o concurrencia
A44: Criterio GWT atómico | B44: DADO QUE [contexto/precondición] · CUANDO [una acción del actor] · ENTONCES [resultado observable y verificable]
A45: Permiso | B45: Código producto.recurso.accion evaluado en la sucursal activa por el módulo de seguridad transversal
A46: Componentes | B46: TR-* = componentes transversales de plataforma · NU-* = núcleos de negocio compartidos por línea de productos
A47: Celdas a completar | B47: En «Criterios GWT», las columnas Estado de prueba y Observaciones (fondo amarillo) son para el equipo de QA

Sheet Aplicaciones
A1: Aplicaciones del sistema (frontends y servicios)
A2: Cada aplicación es un proyecto del monorepo Nx; comparten librerías comunes.
A3: ID | B3: Aplicación | C3: Tipo | D3: Tecnología / proyecto Nx | E3: Usuarios | F3: Descripción | G3: N.° RF
A4: APP-01 | B4: Consola de plataforma | C4: Backoffice web | D4: Angular 19 · app Nx plataforma-consola | E4: Administrador de plataforma, agente de soporte | F4: Consola del equipo dueño de la plataforma: tenants y suscripciones, catálogos globales y tablas maestras, facturación a clientes, centro de soporte, observabilidad y salud por cliente, eventos fallidos e integridad de auditoría. | G4: =COUNTIF(RF!C:C,"APP-01*") -> 23
A5: APP-02 | B5: Administración del cliente (embebible) | C5: Backoffice web | D5: Angular 19 · librería Nx plataforma-admin-cliente (rutas lazy embebidas en <cod>-backoffice) | E5: Administrador del cliente, encargado de facturación, editor de contenidos, oficial de datos personales | F5: Módulo de administración que cada producto monta en su backoffice: empresas, sucursales y unidades, usuarios, roles y perfiles, parámetros, catálogos propios, series, configuración de facturación y pagos, plantillas, CMS del sitio público, auditoría y derechos ARCO. | G5: =COUNTIF(RF!C:C,"APP-02*") -> 43
A6: APP-03 | B6: API de servicios de plataforma | C6: Servicio | D6: NestJS 11 · módulos transversales del monolito modular + workers BullMQ | E6: Módulos de producto, workers, integradores externos | F6: Puertos y adaptadores de los componentes TR expuestos como API interna (inyección de módulos NestJS), REST /v1 y eventos de dominio; incluye los workers de emisión de comprobantes, mensajes, reportes, despacho de eventos y evaluación de alertas. | G6: =COUNTIF(RF!C:C,"APP-03*") -> 55
A7: APP-04 | B7: Agente local (edge) | C7: Servicio | D7: Node.js 22 LTS · app Nx plataforma-edge (instalador Windows/Linux, SQLite cifrado) | E7: Equipos del local del cliente (POS, kiosco, pantallas) | F7: Servicio instalado en el local para impresión térmica, cajón de dinero, dispositivos (biométrico, kiosko, pantallas), operación sin internet con cola local y sincronización con la nube. | G7: =COUNTIF(RF!C:C,"APP-04*") -> 4
A8: APP-05 | B8: Librerías Angular compartidas y shell del portal | C8: Servicio | D8: Angular 19 · librerías Nx ui-diseno, shell-backoffice, seguridad-cliente, portal-shell, soporte-widget | E8: Usuarios internos de los productos y clientes finales en los <cod>-web | F8: Sistema de diseño, shell de backoffice (selector de sucursal, menú por permisos, notificaciones), cliente de seguridad OIDC, shell del portal del cliente final (registro, OTP, perfil, consentimientos) y widget de soporte con contexto automático. | G8: =COUNTIF(RF!C:C,"APP-05*") -> 13

Sheet Módulos
A1: Módulos funcionales
A3: ID | B3: Módulo | C3: Aplicación | D3: Descripción | E3: N.° RF
A4: MOD-01 | B4: Organización y suscripciones (TR-ORG) | C4: APP-01 · Consola de plataforma | D4: Tenant, empresa, sucursal, unidad operativa, suscripción por producto, límites y facturación de la plataforma. | E4: =COUNTIF(RF!B:B,"MOD-01*") -> 7
A5: MOD-02 | B5: Seguridad y accesos (TR-SEG) | C5: APP-02 · Administración del cliente (embebible) | D5: Manifiesto funcional, usuarios, membresías, roles, perfiles, asignaciones con alcance, permisos efectivos, MFA, sesiones y acceso de soporte. | E5: =COUNTIF(RF!B:B,"MOD-02*") -> 14
A6: MOD-03 | B6: Catálogos y tablas maestras (TR-CAT) | C6: APP-01 · Consola de plataforma | D6: Catálogos globales, mixtos y por tenant, ítems con vigencia, personalización por tenant, tablas oficiales y feriados. | E6: =COUNTIF(RF!B:B,"MOD-03*") -> 8
A7: MOD-04 | B7: Parámetros jerárquicos (TR-CFG) | C7: APP-02 · Administración del cliente (embebible) | D7: Definición, valores por alcance, resolución con herencia e historial de parámetros. | E7: =COUNTIF(RF!B:B,"MOD-04*") -> 5
A8: MOD-05 | B8: Correlativos y series (TR-SEQ) | C8: APP-02 · Administración del cliente (embebible) | D8: Series por alcance, numeración atómica, reinicio por periodo y bloques para operación offline. | E8: =COUNTIF(RF!B:B,"MOD-05*") -> 4
A9: MOD-06 | B9: Personas (TR-PER) | C9: APP-03 · API de servicios de plataforma | D9: Maestro de personas naturales y jurídicas por tenant, contactos, direcciones, roles por producto, duplicados y consentimientos. | E9: =COUNTIF(RF!B:B,"MOD-06*") -> 5
A10: MOD-07 | B10: Identidad e interoperabilidad (TR-IDN) | C10: APP-03 · API de servicios de plataforma | D10: Validación y consulta DNI/RUC con caché, proveedores, cuota y bitácora; identidad portable autorizada por el titular. | E10: =COUNTIF(RF!B:B,"MOD-07*") -> 8
A11: MOD-08 | B11: Facturación electrónica (TR-FE) | C11: APP-03 · API de servicios de plataforma | D11: Emisor, comprobantes UBL 2.1, envío a PSE/OSE, CDR, resumen diario, baja, contingencia, PDF y monitoreo. | E11: =COUNTIF(RF!B:B,"MOD-08*") -> 13
A12: MOD-09 | B12: Pagos y conciliación (TR-PAG) | C12: APP-03 · API de servicios de plataforma | D12: Pasarelas, intención de cobro, Yape/Plin, links de pago, webhooks, reembolsos, recurrencia y conciliación. | E12: =COUNTIF(RF!B:B,"MOD-09*") -> 9
A13: MOD-10 | B13: Notificaciones (TR-NOT) | C13: APP-03 · API de servicios de plataforma | D13: Plantillas multicanal, envío transaccional, recordatorios, preferencias, plantillas WhatsApp y estados de entrega. | E13: =COUNTIF(RF!B:B,"MOD-10*") -> 6
A14: MOD-11 | B14: Archivos (TR-ARC) | C14: APP-03 · API de servicios de plataforma | D14: Carga validada, versiones, URLs firmadas, retención y bloqueo legal. | E14: =COUNTIF(RF!B:B,"MOD-11*") -> 4
A15: MOD-12 | B15: Auditoría y datos personales (TR-AUD) | C15: APP-03 · API de servicios de plataforma | D15: Auditoría inmutable, accesos sensibles, integridad, solicitudes ARCO e incidentes de seguridad. | E15: =COUNTIF(RF!B:B,"MOD-12*") -> 8
A16: MOD-13 | B16: Eventos de dominio (TR-EVT) | C16: APP-03 · API de servicios de plataforma | D16: Outbox transaccional, catálogo de eventos, despacho a suscriptores, reintentos y cola de eventos fallidos. | E16: =COUNTIF(RF!B:B,"MOD-13*") -> 4
A17: MOD-14 | B17: Reportes y tableros (TR-REP) | C17: APP-03 · API de servicios de plataforma | D17: Definición declarativa de reportes, ejecución y exportación, programación de envíos y tableros por rol. | E17: =COUNTIF(RF!B:B,"MOD-14*") -> 4
A18: MOD-15 | B18: Servicios de IA (TR-IA) | C18: APP-03 · API de servicios de plataforma | D18: Pasarela de modelos, enmascaramiento, extracción documental, RAG, agente conversacional, copiloto analítico y control de consumo. | E18: =COUNTIF(RF!B:B,"MOD-15*") -> 6
A19: MOD-16 | B19: Observabilidad (TR-OBS) | C19: APP-01 · Consola de plataforma | D19: Indicadores de negocio por minuto, reglas de alerta, evaluación, salud por tenant y sucursal. | E19: =COUNTIF(RF!B:B,"MOD-16*") -> 5
A20: MOD-17 | B20: Centro de soporte (TR-SOP) | C20: APP-01 · Consola de plataforma | D20: Tickets con contexto, SLA por plan, ciclo de vida, escalamiento, problemas en GitHub y base de conocimiento. | E20: =COUNTIF(RF!B:B,"MOD-17*") -> 8
A21: MOD-18 | B21: Gestor de contenidos web (TR-CMS) | C21: APP-02 · Administración del cliente (embebible) | D21: Sitio público por tenant: dominio, marca, páginas por bloques, menús, medios, noticias, SEO, formularios y versiones. | E21: =COUNTIF(RF!B:B,"MOD-18*") -> 6
A22: MOD-19 | B22: Portal del cliente final (TR-POR) | C22: APP-05 · Librerías Angular compartidas y shell del portal | D22: Registro y acceso de clientes externos, perfil, consentimientos y vista consolidada de transacciones. | E22: =COUNTIF(RF!B:B,"MOD-19*") -> 5
A23: MOD-20 | B23: Integración externa (TR-INT) | C23: APP-03 · API de servicios de plataforma | D23: Clientes de API, API pública versionada, webhooks salientes y sincronización con bases institucionales. | E23: =COUNTIF(RF!B:B,"MOD-20*") -> 4
A24: MOD-21 | B24: Agente local (TR-EDGE) | C24: APP-04 · Agente local (edge) | D24: Enrolamiento, impresión térmica, cajón, cola offline, sincronización, dispositivos y actualización remota. | E24: =COUNTIF(RF!B:B,"MOD-21*") -> 5

Sheet Actores
A1: Actores
A3: ID | B3: Actor | C3: Tipo | D3: Descripción
A4: ACT-01 | B4: Administrador de plataforma | C4: Interno | D4: Integrante del equipo dueño de la plataforma; da de alta clientes, gestiona suscripciones, catálogos globales y operación.
A5: ACT-02 | B5: Agente de soporte (N1/N2) | C5: Interno | D5: Atiende tickets de los clientes de los nueve productos; N2 analiza causa raíz y coordina con ingeniería.
A6: ACT-03 | B6: Administrador del cliente | C6: Interno | D6: Usuario propietario o administrador del tenant; configura empresas, sucursales, usuarios, roles y parámetros.
A7: ACT-04 | B7: Usuario operativo del producto | C7: Interno | D7: Cajero, recepcionista, mozo, operador de ventanilla o asistente que usa un producto apoyado en la plataforma.
A8: ACT-05 | B8: Cliente final / titular de datos | C8: Externo | D8: Persona natural o jurídica atendida por un tenant (cliente, paciente, socio, administrado) y titular de sus datos personales.
A9: ACT-06 | B9: Encargado de facturación del cliente | C9: Interno | D9: Contador o asistente que configura el emisor electrónico y monitorea comprobantes y conciliaciones.
A10: ACT-07 | B10: Editor de contenidos web | C10: Interno | D10: Usuario del cliente que administra páginas, noticias, banners y SEO del sitio público.
A11: ACT-08 | B11: Módulo de producto consumidor | C11: Sistema externo | D11: Módulo NestJS de un producto (rest, psi, col, lib, gym, cli, doc, eco, lex) o núcleo que invoca los puertos de la plataforma.
A12: ACT-09 | B12: PSE/OSE y SUNAT | C12: Sistema externo | D12: Proveedor de servicios electrónicos u operador de servicios electrónicos que valida y envía comprobantes a SUNAT y devuelve el CDR.
A13: ACT-10 | B13: Pasarela de pagos | C13: Sistema externo | D13: Procesador de tarjetas, billeteras Yape/Plin y links de pago que notifica por webhook firmado.
A14: ACT-11 | B14: Proveedor de identidad pública | C14: Sistema externo | D14: Convenio RENIEC o proveedor autorizado de consulta DNI y padrón RUC de SUNAT.
... A21: ACT-18 | B21: Responsable de datos personales del cliente | C21: Interno | D21: Persona designada por el tenant para atender derechos ARCO, consentimientos e incidentes ante la ANPD.

Sheet Procesos
A1: Procesos de negocio
A3: ID | B3: Proceso | C3: Descripción | D3: Actores | E3: Disparador | F3: Pasos | G3: Resultado | H3: N.° RF
A4: TR-P01 | B4: Alta y configuración de tenant | C4: Incorporación de un nuevo cliente: tenant, suscripción, empresa, sucursales, unidades y usuario administrador, hasta dejarlo operativo en su producto. | D4: Administrador de plataforma, Administrador del cliente, Proveedor de identidad OIDC (IdP), Proveedor de mensajería, Planificador de tareas | E4: Firma de contrato o registro de prueba gratuita | F4: 1. El administrador de plataforma inicia el asistente de alta con el nombre comercial y el producto contratado. 2. El sistema crea el tenant en estado PRUEBA o ACTIVO y la suscripción con plan y límites. 3. Se registra la empresa con su RUC validado contra el padrón y su sucursal principal (establecimiento 0000). 4. Se invita al administrador del cliente; el IdP crea la cuenta y el sistema la vincula como propietario. 5. El administrador del cliente completa sucursales, unidades operativas, parámetros y series. 6. El planificador controla vencimientos de prueba y suscripción y notifica antes del corte. | G4: Tenant activo con suscripción vigente, estructura organizacional y administrador con acceso | H4: =COUNTIF('Matriz Proceso-RF'!D:D,"●") -> 13
A5: TR-P02 | B5: Gestión de seguridad y accesos | C5: Administración de usuarios, membresías, roles, perfiles y asignaciones con alcance, incluido el acceso temporal del equipo de soporte. | D5: Administrador del cliente, Usuario operativo del producto, Proveedor de identidad OIDC (IdP), Agente de soporte (N1/N2), Módulo de producto consumidor | E5: Ingreso, cambio de puesto o salida de un colaborador; despliegue de una nueva versión de producto | F5: 1. El despliegue aplica el manifiesto del producto (módulos, opciones, permisos). 2. El administrador del cliente invita al usuario y le asigna un perfil o rol con alcance y vigencia. 3. El usuario acepta la invitación y se autentica en el IdP. 4. Al iniciar sesión elige empresa y sucursal; el sistema calcula permisos efectivos y menú. 5. Las acciones sensibles exigen MFA reciente y quedan auditadas. 6. Las asignaciones se revocan o vencen y las sesiones se cierran cuando corresponde. | G5: Usuarios con permisos efectivos acordes a su puesto y alcance, con trazabilidad completa | H5: =COUNTIF('Matriz Proceso-RF'!E:E,"●") -> 14
A6: TR-P03 | B6: Gestión de catálogos y parámetros | C6: Mantenimiento de catálogos globales y propios, tablas maestras oficiales, parámetros jerárquicos y series de numeración. | D6: Administrador de plataforma, Administrador del cliente, Módulo de producto consumidor | E6: Cambio normativo, nueva versión de tabla oficial o necesidad de configuración del cliente | F6: 1. El administrador de plataforma actualiza catálogos globales o importa la nueva versión de una tabla oficial. 2. El sistema publica catalogo.actualizado e invalida cachés. 3. El administrador del cliente ajusta ítems globales o registra ítems propios en catálogos mixtos. 4. El administrador del cliente define valores de parámetros por alcance y series por establecimiento. 5. Los productos resuelven catálogos, parámetros y correlativos mediante los puertos de la plataforma. | G6: Catálogos, parámetros y series vigentes y consistentes para todos los productos | H6: =COUNTIF('Matriz Proceso-RF'!F:F,"●") -> 19
A7: TR-P04 | B7: Emisión de comprobantes electrónicos | C7: Generación, firma, envío y seguimiento de comprobantes electrónicos SUNAT desde cualquier producto. | D7: Módulo de producto consumidor, Encargado de facturación del cliente, PSE/OSE y SUNAT, Cliente final / titular de datos, Planificador de tareas | E7: Un producto confirma una venta o un ajuste que requiere comprobante | F7: 1. El producto solicita la emisión con los datos de la venta y el tipo de comprobante. 2. El sistema valida adquirente, montos e impuestos y asigna serie y número. 3. Se genera el XML UBL 2.1, se firma con el certificado del emisor y se encola el envío. 4. El worker envía al PSE/OSE y procesa el CDR o la respuesta de error. 5. Las boletas se informan en resumen diario y las anulaciones con comunicación de baja o nota de crédito. 6. Se genera la representación impresa y se envía al cliente; los pendientes se monitorean hasta su estado final. | G7: Comprobante aceptado con CDR, PDF disponible y entregado al cliente, o incidencia gestionada | H7: =COUNTIF('Matriz Proceso-RF'!G:G,"●") -> 19
A8: TR-P05 | B8: Cobros y conciliación | C8: Cobro a clientes finales con medios electrónicos, confirmación por webhook, reembolsos, cobros recurrentes y conciliación con la liquidación de la pasarela; incluye el cobro de la suscripción del tenant. | D8: Módulo de producto consumidor, Usuario operativo del producto, Cliente final / titular de datos, Pasarela de pagos, Encargado de facturación del cliente, Administrador de plataforma | E8: Una venta, cita, membresía o pedido requiere cobro electrónico; cierre diario de liquidaciones | F8: 1. El producto crea una intención de cobro o un link de pago. 2. El cliente paga con tarjeta, Yape o Plin en la pasarela. 3. La pasarela notifica por webhook firmado; el sistema confirma el pago y publica pago.confirmado. 4. Los reembolsos se solicitan con motivo y se confirman por webhook. 5. Diariamente se importa la liquidación y se concilia contra los pagos registrados. | G8: Pagos confirmados, reembolsos registrados y diferencias de conciliación identificadas | H8: =COUNTIF('Matriz Proceso-RF'!H:H,"●") -> 13
A9: TR-P06 | B9: Envío de notificaciones | C9: Comunicación con clientes finales y usuarios internos por correo, SMS, WhatsApp y push, transaccional o programada. | D9: Módulo de producto consumidor, Administrador del cliente, Cliente final / titular de datos, Proveedor de mensajería, Planificador de tareas | E9: Un evento de negocio o un recordatorio programado requiere avisar a una persona | F9: 1. El producto solicita el envío indicando plantilla, destinatario y variables, o programa un recordatorio. 2. El sistema verifica preferencias, consentimiento y bajas del destinatario. 3. Renderiza la plantilla del canal y la entrega al proveedor de mensajería. 4. Recibe el estado de entrega; ante fallo reintenta o cambia de canal. 5. El destinatario gestiona sus preferencias o se da de baja. | G9: Mensaje entregado por el canal preferido o fallo registrado con reintento | H9: =COUNTIF('Matriz Proceso-RF'!I:I,"●") -> 11
A10: TR-P07 | B10: Gestión de contenidos web (CMS) | C10: Construcción y publicación del sitio público del tenant y del portal del cliente final. | D10: Editor de contenidos web, Administrador del cliente, Cliente final / titular de datos | E10: El cliente necesita publicar o actualizar su sitio, campañas o información | F10: 1. El administrador configura dominio o subdominio y la identidad de marca. 2. El editor crea páginas por bloques, menús, medios y noticias. 3. Previsualiza y publica de inmediato o programa la publicación. 4. El sitio se sirve por SSR con caché e invalidación al publicar. 5. Los visitantes envían formularios y se registran en el portal del cliente. | G10: Sitio publicado en su dominio con contenido vigente, SEO y formularios operativos | H10: =COUNTIF('Matriz Proceso-RF'!J:J,"●") -> 13
A11: TR-P08 | B11: Atención de soporte | C11: Gestión de tickets de los clientes de los nueve productos desde su registro hasta el cierre, con SLA por plan. | D11: Usuario operativo del producto, Administrador del cliente, Agente de soporte (N1/N2), GitHub, Planificador de tareas | E11: Un usuario reporta un incidente o consulta, o una alerta crea un ticket automático | F11: 1. El usuario crea un ticket desde el widget; el sistema adjunta contexto técnico y calcula prioridad y plazos. 2. El agente N1 analiza, responde y, si requiere, pide información al cliente (pausa de SLA). 3. Si no lo resuelve, escala a N2 y se vincula a un problema con issue en GitHub. 4. Al publicar la corrección se resuelve el problema y sus tickets. 5. El cliente confirma o el ticket se cierra automáticamente. | G11: Ticket resuelto dentro del SLA, problema raíz enlazado y cliente informado | H11: =COUNTIF('Matriz Proceso-RF'!K:K,"●") -> 10
A12: TR-P09 | B12: Observabilidad y alertas | C12: Medición de indicadores de negocio por cliente y sucursal, detección de anomalías y alerta temprana. | D12: Planificador de tareas, Administrador de plataforma, Agente de soporte (N1/N2), Administrador del cliente | E12: Eventos de dominio de los productos; ejecución programada del evaluador cada minuto | F12: 1. Los productos declaran indicadores en su manifiesto. 2. El consumidor de eventos registra la métrica por minuto. 3. El evaluador compara contra umbrales, ausencia de datos o línea base. 4. Abre o resuelve alertas, notifica y crea tickets si la regla lo indica. 5. El equipo revisa el tablero de salud por tenant y sucursal. | G12: Alertas abiertas y resueltas automáticamente, salud por cliente visible y tickets creados cuando corresponde | H12: =COUNTIF('Matriz Proceso-RF'!L:L,"●") -> 11
A13: TR-P10 | B13: Consulta de identidad e interoperabilidad | C13: Identificación de personas con DNI/RUC, maestro de personas compartido entre productos del tenant e identidad portable autorizada por el titular. | D13: Usuario operativo del producto, Módulo de producto consumidor, Proveedor de identidad pública, Cliente final / titular de datos | E13: Registro de un cliente, paciente o socio, o emisión de un comprobante que requiere identificar al adquirente | F13: 1. El usuario digita el tipo y número de documento. 2. El sistema valida el formato y busca en caché; si no existe, consulta al proveedor con control de cuota. 3. Registra o reutiliza la persona del tenant y le asigna el rol del producto. 4. Si el titular tiene identidad portable, el tenant solicita autorización y el titular la confirma con un código. 5. El sistema entrega solo los campos autorizados y registra cada acceso. | G13: Persona identificada con datos de fuente oficial y, si el titular autoriza, datos portables incorporados | H13: =COUNTIF('Matriz Proceso-RF'!M:M,"●") -> 17
A14: TR-P11 | B14: Auditoría y cumplimiento de datos personales (ARCO) | C14: Registro inmutable de operaciones críticas, atención de derechos ARCO, consentimientos e incidentes conforme a la Ley 29733. | D14: Administrador del cliente, Responsable de datos personales del cliente, Cliente final / titular de datos, Administrador de plataforma | E14: Operación crítica, acceso a dato sensible, solicitud del titular o incidente de seguridad | F14: 1. Los productos registran operaciones críticas y accesos sensibles en la auditoría. 2. El titular presenta una solicitud ARCO desde el portal o el tenant la registra. 3. El responsable compila los datos, decide y responde dentro del plazo legal. 4. Las cancelaciones anonimizan respetando plazos de conservación obligatoria. 5. Los incidentes se registran y se notifican a la ANPD y a los titulares cuando corresponde. | G14: Evidencia íntegra y verificable; solicitudes atendidas en plazo; incidentes notificados | H14: =COUNTIF('Matriz Proceso-RF'!N:N,"●") -> 23
A15: TR-P12 | B15: Integración externa y sincronización | C15: Intercambio con sistemas de terceros y bases institucionales mediante eventos, API pública, webhooks y el agente local. | D15: Módulo de producto consumidor, Sistema institucional o integrador, Planificador de tareas, Administrador de plataforma, Usuario operativo del producto | E15: Cambio de un agregado de negocio, solicitud de un integrador o recuperación de conectividad del local | F15: 1. El módulo de producto publica el evento en el outbox dentro de su transacción. 2. El despachador entrega el evento a suscriptores internos y webhooks salientes. 3. Los conectores institucionales leen por cursor y confirman el último evento procesado. 4. El agente local sincroniza su cola offline y descarga configuración. 5. Se concilian conteos diarios y se reprocesan los eventos fallidos. | G15: Sistemas externos y locales sincronizados, con entrega confirmada y conciliación diaria | H15: =COUNTIF('Matriz Proceso-RF'!O:O,"●") -> 16
A16: TR-P13 | B16: Reportes y analítica | C16: Generación de reportes operativos y de gestión, tableros por rol y análisis asistido por IA. | D16: Administrador del cliente, Usuario operativo del producto, Encargado de facturación del cliente, Planificador de tareas, Proveedor de modelos de IA | E16: Necesidad de información de gestión o envío programado | F16: 1. El producto declara sus reportes y tableros en el manifiesto. 2. El usuario selecciona un reporte, define filtros y lo ejecuta o programa. 3. El motor aplica alcance y permisos, ejecuta la consulta y genera Excel o PDF. 4. Los reportes programados se envían por correo; el copiloto responde preguntas con consultas predefinidas. | G16: Reporte o tablero entregado con datos del alcance permitido al usuario | H16: =COUNTIF('Matriz Proceso-RF'!P:P,"●") -> 13

Sheet Reglas de negocio
A1: Reglas de negocio
A3: ID | B3: Regla | C3: Tipo | D3: Fuente
A4: TR-RN-001 | B4: Toda entidad de negocio pertenece a la jerarquía tenant → empresa (RUC) → sucursal (establecimiento) → unidad operativa y lleva tenant_id; ninguna consulta puede cruzar tenants. | C4: Negocio | D4: ADR de arquitectura multi-tenant; transversal/sql/01_org
A5: TR-RN-002 | B5: El RUC tiene 11 dígitos, inicia con 10, 15, 17 o 20 y su último dígito cumple el algoritmo módulo 11 de SUNAT; el DNI tiene 8 dígitos numéricos. | C5: Validación | D5: SUNAT (algoritmo de dígito verificador); RENIEC
A6: TR-RN-003 | B6: Cada empresa tiene exactamente una sucursal principal; el código de establecimiento SUNAT tiene 4 dígitos y el domicilio fiscal es 0000. | C6: Validación | D6: SUNAT — establecimientos anexos del RUC
A7: TR-RN-004 | B7: Una unidad operativa debe pertenecer a una sucursal, salvo las de tipo ALMACEN, que pueden pertenecer directamente a la empresa (almacén central). | C7: Validación | D7: transversal/sql/01_org (ck_unidad_sin_sucursal)
A8: TR-RN-005 | B8: Estados del tenant: PRUEBA → ACTIVO → SUSPENDIDO → BAJA. Un tenant SUSPENDIDO solo permite lectura, pago de deuda, exportación de datos y soporte; BAJA conserva los datos 90 días antes de su eliminación definitiva. | C8: Negocio | D8: Política comercial de la plataforma
A9: TR-RN-006 | B9: Un producto sin suscripción vigente (ACTIVA o PRUEBA) no otorga permisos; no se pueden crear sucursales ni usuarios por encima de los límites del plan. | C9: Negocio | D9: transversal/sql/02_seg (permisos_efectivos); contrato de suscripción
A10: TR-RN-007 | B10: Los permisos tienen el código producto.recurso.accion y se evalúan por alcance: TENANT cubre todas las empresas y sucursales; EMPRESA, sus sucursales y unidades; SUCURSAL, sus unidades; UNIDAD, solo esa unidad. Los permisos PLAT no dependen de suscripción. | C10: Negocio | D10: transversal/sql/02_seg
A11: TR-RN-008 | B11: Una asignación tiene un rol o un perfil, nunca ambos ni ninguno, y su alcance debe ser coherente con la empresa, sucursal o unidad informada; la vigencia hasta no puede ser anterior a la vigencia desde. | C11: Validación | D11: transversal/sql/02_seg (ck_asig_rol_o_perfil, ck_asig_alcance)
A12: TR-RN-009 | B12: Los permisos marcados como sensibles (anular, reembolsar, exportar datos personales, cambiar series, otorgar roles) exigen MFA con antigüedad máxima de 15 minutos y quedan auditados. | C12: Negocio | D12: TR-RNF-009; política de seguridad
A13: TR-RN-010 | B13: Todo tenant debe tener al menos un propietario con membresía ACTIVA; no se puede suspender, revocar ni dar de baja al último propietario. | C13: Negocio | D13: Política de seguridad de la plataforma
A14: TR-RN-011 | B14: El acceso del equipo de soporte a datos de un tenant requiere autorización expresa del administrador del cliente, con motivo, ticket asociado y vigencia máxima de 4 horas; cada acción se audita como ACCESO_SOPORTE. | C14: Negocio | D14: Ley 29733 (encargado de tratamiento); TR-RNF-013
... A51: TR-RN-048 | B51: Un incidente de seguridad que afecte datos personales se registra y se notifica a la Autoridad Nacional de Protección de Datos Personales dentro de las 48 horas de conocido. | C51: Normativa | D51: D.S. N.° 016-2024-JUS (verificar artículo)

Sheet RF
A1: Requerimientos funcionales
A2: Un requerimiento = una capacidad verificable. Los criterios de aceptación están en la hoja «Criterios GWT».
A3: ID | B3: Módulo | C3: Aplicación | D3: Nombre | E3: Descripción | F3: Actores | G3: Permiso | H3: Precondiciones | I3: Flujo básico | J3: Datos y validaciones | K3: Reglas | L3: Salida | M3: Prioridad | N3: Fase | O3: Procesos | P3: Componentes | Q3: RNF | R3: IA | S3: N.° criterios
A4: TR-RF-001 | B4: MOD-01 · Organización y suscripciones (TR-ORG) | C4: APP-01 · Consola de plataforma | D4: Dar de alta un tenant con asistente | E4: El sistema debe permitir al administrador de plataforma crear un tenant mediante un asistente que registra en una sola operación el tenant, la suscripción inicial, la empresa con su RUC, la sucursal principal y la invitación al propietario. | F4: Administrador de plataforma | G4: plat.tenant.crear | H4: El administrador de plataforma tiene sesión con MFA vigente y el producto contratado existe en seg.producto. | I4: 1. El actor ingresa código y nombre del tenant, producto, plan y modalidad (prueba o activo). 2. El actor ingresa RUC, razón social y correo del propietario. 3. El sistema valida el RUC (TR-RN-002) y consulta el padrón mediante TR-IDN para completar razón social y domicilio fiscal. 4. El sistema crea tenant, suscripción, empresa y sucursal principal con establecimiento 0000 en una transacción. 5. El sistema siembra parámetros por defecto, series iniciales y roles predefinidos del producto. 6. El sistema invita al propietario por correo y publica tenant.creado. | J4: codigo (texto 3-30, único, minúsculas y guiones); nombre (texto 3-150, obligatorio); producto_codigo (catálogo de productos, obligatorio); plan (BASICO|PRO|EMPRESA); modalidad (PRUEBA|ACTIVO); ruc (11 dígitos, obligatorio); correo_propietario (correo válido, obligatorio) | K4: TR-RN-001, TR-RN-002, TR-RN-003, TR-RN-005 | L4: Tenant en estado PRUEBA o ACTIVO con empresa, sucursal principal, suscripción y propietario invitado; tiempo total del asistente < 15 min | M4: Must | N4: MVP | O4: TR-P01 | P4: TR-ORG, TR-SEG, TR-IDN, TR-CFG, TR-SEQ, TR-NOT, TR-EVT | Q4: TR-RNF-029, TR-RNF-010, TR-RNF-008 | R4: No | S4: =COUNTIF('Criterios GWT'!B:B,A4) -> 3
A5: TR-RF-002 | B5: MOD-01 · Organización y suscripciones (TR-ORG) | C5: APP-02 · Administración del cliente (embebible) | D5: Registrar empresa del tenant | E5: El sistema debe permitir al administrador del cliente registrar empresas adicionales (RUC) dentro de su tenant, completando razón social, nombre comercial y domicilio fiscal desde el padrón RUC. | F5: Administrador del cliente | G5: plat.empresa.crear | H5: El tenant está ACTIVO o en PRUEBA y el actor tiene alcance TENANT. | I5: 1. El actor ingresa el RUC de la nueva empresa. 2. El sistema valida el formato y consulta el padrón mediante TR-IDN. 3. El sistema muestra razón social, estado y condición del contribuyente. 4. El actor completa nombre comercial y confirma. 5. El sistema crea la empresa y su sucursal principal con establecimiento 0000 y publica empresa.creada. | J5: ruc (11 dígitos, único por tenant); razon_social (texto 1-200, desde padrón); nombre_comercial (texto 0-150); direccion_fiscal (texto 0-250); ubigeo (6 dígitos, catálogo UBIGEO) | K5: TR-RN-001, TR-RN-002, TR-RN-003, TR-RN-019 | L5: Empresa activa con sucursal principal creada | M5: Must | N5: MVP | O5: TR-P01, TR-P10 | P5: TR-ORG, TR-IDN, TR-CAT, TR-EVT | Q5: TR-RNF-010, TR-RNF-007 | R5: No | S5: =COUNTIF('Criterios GWT'!B:B,A5) -> 3
A6: TR-RF-003 | B6: MOD-01 · Organización y suscripciones (TR-ORG) | C6: APP-02 · Administración del cliente (embebible) | D6: Registrar sucursal (establecimiento) | E6: El sistema debe permitir registrar, editar e inactivar sucursales de una empresa con su código de establecimiento SUNAT, dirección, ubigeo, teléfono y zona horaria, garantizando una sola sucursal principal por empresa. | F6: Administrador del cliente | G6: plat.sucursal.gestionar | H6: La empresa existe y está activa; la suscripción no ha alcanzado su límite de sucursales. | I6: 1. El actor selecciona la empresa y elige nueva sucursal. 2. Ingresa código interno, nombre, código de establecimiento SUNAT, dirección y ubigeo. 3. El sistema valida unicidad del código, formato del establecimiento y límite del plan. 4. El sistema guarda la sucursal y publica sucursal.creada. | J6: codigo (texto 1-20, único por empresa); nombre (texto 3-150); codigo_establecimiento_sunat (4 dígitos, opcional); direccion (texto 0-250); ubigeo (catálogo UBIGEO); telefono (texto 0-30); zona_horaria (IANA, por defecto America/Lima); es_principal (booleano) | K6: TR-RN-001, TR-RN-003, TR-RN-006 | L6: Sucursal activa disponible para asignaciones, series y parámetros | M6: Must | N6: MVP | O6: TR-P01 | P6: TR-ORG, TR-CAT, TR-EVT | Q6: TR-RNF-010, TR-RNF-027 | R6: No | S6: =COUNTIF('Criterios GWT'!B:B,A6) -> 3
A7: TR-RF-004 | B7: MOD-01 · Organización y suscripciones (TR-ORG) | C7: APP-02 · Administración del cliente (embebible) | D7: Registrar unidad operativa | E7: El sistema debe permitir registrar unidades operativas (almacén, caja, punto de venta, consultorio, ventanilla, salón, estación de producción) dentro de una sucursal, o almacenes centrales a nivel de empresa, con atributos propios del tipo. | F7: Administrador del cliente | G7: plat.unidad.gestionar | H7: Existe la sucursal o, si el tipo es ALMACEN, al menos la empresa. | I7: 1. El actor elige la sucursal y el tipo de unidad del catálogo TIPO_UNIDAD. 2. Ingresa código, nombre, unidad padre opcional y atributos. 3. El sistema valida la regla de pertenencia (TR-RN-004) y la unicidad por empresa, tipo y código. 4. El sistema guarda la unidad y publica unidad.creada. | J7: tipo (catálogo TIPO_UNIDAD, obligatorio); codigo (texto 1-20); nombre (texto 3-150); sucursal_id (uuid, obligatorio salvo ALMACEN); padre_id (uuid, opcional); atributos (JSON: impresora, capacidad, piso) | K7: TR-RN-004, TR-RN-001 | L7: Unidad operativa activa asignable a usuarios y numeración | M7: Must | N7: MVP | O7: TR-P01 | P7: TR-ORG, TR-CAT | Q7: TR-RNF-010, TR-RNF-027 | R7: No | S7: =COUNTIF('Criterios GWT'!B:B,A7) -> 3
A8: TR-RF-005 | B8: MOD-01 · Organización y suscripciones (TR-ORG) | C8: APP-01 · Consola de plataforma | D8: Gestionar suscripción de producto | E8: El sistema debe permitir al administrador de plataforma crear y modificar la suscripción de un tenant a un producto, indicando edición, plan, límites de sucursales y usuarios y vigencia, y propagar el cambio a permisos y cuotas. | F8: Administrador de plataforma | G8: plat.suscripcion.gestionar | H8: El tenant existe y no está en BAJA. | I8: 1. El actor abre el tenant y selecciona el producto. 2. Define edición, plan, límites y fecha de vigencia. 3. El sistema valida que los nuevos límites no sean menores que el uso actual. 4. El sistema guarda, invalida la caché de permisos y publica suscripcion.cambiada. | J8: producto_codigo (REST|PSI|COL|LIB|GYM|CLI|DOC|ECO|LEX); edicion (texto 0-30); plan (BASICO|PRO|EMPRESA); estado (PRUEBA|ACTIVA|VENCIDA|CANCELADA); limite_sucursales (entero ≥ 1 o vacío); limite_usuarios (entero ≥ 1 o vacío); vigente_hasta (fecha) | K8: TR-RN-006 | L8: Suscripción actualizada con efecto inmediato en permisos, cuotas y SLA | M8: Must | N8: MVP | O8: TR-P01, TR-P05 | P8: TR-ORG, TR-SEG, TR-EVT | Q8: TR-RNF-101, TR-RNF-027 | R8: No | S8: =COUNTIF('Criterios GWT'!B:B,A8) -> 3
A9: TR-RF-006 | B9: MOD-01 · Organización y suscripciones (TR-ORG) | C9: APP-01 · Consola de plataforma | D9: Cambiar estado del tenant | E9: El sistema debe permitir suspender, reactivar o dar de baja un tenant registrando motivo obligatorio, aplicando las restricciones del estado y notificando al propietario. | F9: Administrador de plataforma | G9: plat.tenant.cambiar_estado | H9: El actor tiene MFA vigente; el tenant existe. | I9: 1. El actor selecciona el nuevo estado e ingresa el motivo. 2. El sistema solicita confirmación explícita. 3. El sistema valida la transición permitida (TR-RN-005). 4. El sistema aplica el estado, cierra sesiones si es SUSPENDIDO o BAJA, registra auditoría y notifica al propietario. | J9: estado_nuevo (ACTIVO|SUSPENDIDO|BAJA); motivo (texto 10-500, obligatorio); fecha_efectiva (fecha-hora, por defecto ahora) | K9: TR-RN-005, TR-RN-009 | L9: Tenant en el nuevo estado con restricciones aplicadas y notificación enviada | M9: Must | N9: MVP | O9: TR-P01, TR-P05 | P9: TR-ORG, TR-SEG, TR-AUD, TR-NOT | Q9: TR-RNF-021, TR-RNF-013 | R9: No | S9: =COUNTIF('Criterios GWT'!B:B,A9) -> 3
A10: TR-RF-007 | B10: MOD-01 · Organización y suscripciones (TR-ORG) | C10: APP-03 · API de servicios de plataforma | D10: Controlar vencimiento de prueba y suscripción | E10: El sistema debe ejecutar diariamente el control de vencimientos: avisar al propietario 7, 3 y 1 días antes, pasar la suscripción a VENCIDA al vencer y suspender el tenant tras el periodo de gracia configurado. | F10: Planificador de tareas | G10: plat.sistema.job | H10: El job programado está activo; existen suscripciones con vigente_hasta. | I10: 1. El planificador ejecuta el control a las 06:00 hora de Lima. 2. El sistema identifica suscripciones que vencen en 7, 3 y 1 días y envía avisos. 3. Las suscripciones vencidas pasan a VENCIDA y se publica suscripcion.vencida. 4. Si el periodo de gracia (parámetro plat.suscripcion.dias_gracia) terminó sin pago, se suspende el tenant. | J10: dias_gracia (parámetro NUMERO, por defecto 5); fecha_ejecucion (fecha); resultados (lista de tenant, producto, acción) | K10: TR-RN-005, TR-RN-006 | L10: Suscripciones y tenants con estado actualizado y avisos enviados | M10: Must | N10: MVP | O10: TR-P01, TR-P05 | P10: TR-ORG, TR-NOT, TR-CFG, TR-EVT | Q10: TR-RNF-005, TR-RNF-008 | R10: No | S10: =COUNTIF('Criterios GWT'!B:B,A10) -> 3
A11: TR-RF-008 | B11: MOD-02 · Seguridad y accesos (TR-SEG) | C11: APP-03 · API de servicios de plataforma | D11: Aplicar manifiesto funcional del producto | E11: El sistema debe aplicar en cada despliegue el manifiesto declarativo de un producto (módulos, opciones de menú, permisos con alcance mínimo y sensibilidad, roles predefinidos, parámetros, indicadores y reportes) de forma idempotente. | F11: Planificador de tareas, Administrador de plataforma | G11: plat.manifiesto.aplicar | H11: El pipeline de despliegue dispone del manifiesto versionado del producto. | I11: 1. El pipeline envía el manifiesto con su versión. 2. El sistema valida su esquema y que los códigos de permiso cumplan producto.recurso.accion. 3. El sistema calcula diferencias contra lo registrado. 4. Inserta o actualiza módulos, opciones, permisos y roles predefinidos; marca como obsoletos los retirados. 5. Registra la versión aplicada y publica manifiesto.aplicado. | J11: producto_codigo (5 caracteres); version (semver); modulos[]; opciones[] (codigo, ruta, icono, permisos requeridos); permisos[] (codigo, descripcion, alcance_minimo, sensible); roles_predefinidos[]; parametros[]; indicadores[]; reportes[] | K11: TR-RN-007 | L11: Catálogo funcional del producto sincronizado con la versión desplegada | M11: Must | N11: MVP | O11: TR-P02, TR-P03 | P11: TR-SEG, TR-CFG, TR-OBS, TR-REP, TR-EVT | Q11: TR-RNF-120, TR-RNF-119, TR-RNF-024 | R11: No | S11: =COUNTIF('Criterios GWT'!B:B,A11) -> 3
A12: TR-RF-009 | B12: MOD-02 · Seguridad y accesos (TR-SEG) | C12: APP-02 · Administración del cliente (embebible) | D12: Invitar usuario al tenant | E12: El sistema debe permitir al administrador del cliente invitar a una persona por correo para que se una al tenant, indicando el perfil o rol inicial y su alcance, respetando el límite de usuarios del plan. | F12: Administrador del cliente | G12: plat.usuario.invitar | H12: El actor tiene alcance suficiente para el alcance que otorga; el plan no alcanzó su límite de usuarios. | I12: 1. El actor ingresa correo, nombre y perfil o rol con alcance. 2. El sistema verifica el límite de usuarios del plan. 3. Si el correo no existe en seg.usuario lo crea; crea la membresía en estado INVITADO y la asignación propuesta. 4. El sistema envía la invitación con enlace de un solo uso válido por 72 horas. | J12: correo (correo válido, obligatorio); nombre (texto 3-150); perfil_id o rol_id (uno obligatorio); alcance (TENANT|EMPRESA|SUCURSAL|UNIDAD); empresa_id/sucursal_id/unidad_id (según alcance); vigente_hasta (fecha opcional) | K12: TR-RN-006, TR-RN-008 | L12: Membresía INVITADO creada e invitación enviada | M12: Must | N12: MVP | O12: TR-P02 | P12: TR-SEG, TR-NOT, TR-ORG | Q12: TR-RNF-009, TR-RNF-013 | R12: No | S12: =COUNTIF('Criterios GWT'!B:B,A12) -> 3
A13: TR-RF-010 | B13: MOD-02 · Seguridad y accesos (TR-SEG) | C13: APP-05 · Librerías Angular compartidas y shell del portal | D13: Aceptar invitación y vincular identidad | E13: El sistema debe permitir que el invitado acepte la invitación autenticándose en el IdP (OIDC) y que su identificador (sub) quede vinculado a su usuario, activando la membresía. | F13: Usuario operativo del producto, Proveedor de identidad OIDC (IdP) | G13: publico.invitacion.aceptar | H13: La invitación está vigente y no fue usada. | I13: 1. El invitado abre el enlace de invitación. 2. El shell redirige al IdP para iniciar sesión o crear la cuenta. 3. El IdP devuelve el token con sub y correo verificado. 4. El sistema verifica que el correo coincida con la invitación y activa la membresía y su asignación. 5. El sistema registra el evento ASIGNACION_OTORGADA. | J13: token_invitacion (cadena de un solo uso); sub (uuid del IdP); correo_verificado (booleano) | K13: TR-RN-008 | L13: Membresía ACTIVA y usuario con acceso al producto | M13: Must | N13: MVP | O13: TR-P02 | P13: TR-SEG, TR-AUD | Q13: TR-RNF-009, TR-RNF-014 | R13: No | S13: =COUNTIF('Criterios GWT'!B:B,A13) -> 3
A14: TR-RF-011 | B14: MOD-02 · Seguridad y accesos (TR-SEG) | C14: APP-02 · Administración del cliente (embebible) | D14: Gestionar roles propios del tenant | E14: El sistema debe permitir crear, copiar desde un rol predefinido, editar e inactivar roles propios de un producto, seleccionando sus permisos del catálogo del producto; los roles predefinidos no son editables. | F14: Administrador del cliente | G14: plat.rol.gestionar | H14: El tenant tiene suscripción vigente al producto del rol. | I14: 1. El actor elige el producto y crea un rol nuevo o copia uno predefinido. 2. Marca los permisos del árbol módulo → opción → permiso. 3. El sistema valida que todos los permisos pertenezcan al producto. 4. El sistema guarda el rol, invalida la caché de permisos de los usuarios afectados y registra auditoría. | J14: producto_codigo (obligatorio); codigo (texto 3-50, único por tenant); nombre (texto 3-100); permisos[] (códigos del producto); activo (booleano) | K14: TR-RN-007, TR-RN-009 | L14: Rol propio disponible para asignación | M14: Must | N14: MVP | O14: TR-P02 | P14: TR-SEG, TR-AUD | Q14: TR-RNF-101, TR-RNF-122, TR-RNF-013 | R14: No | S14: =COUNTIF('Criterios GWT'!B:B,A14) -> 3
A15: TR-RF-012 | B15: MOD-02 · Seguridad y accesos (TR-SEG) | C15: APP-02 · Administración del cliente (embebible) | D15: Gestionar perfiles de puesto | E15: El sistema debe permitir definir perfiles de puesto que agrupen roles de uno o varios productos contratados, para asignar con una sola operación el acceso completo de un puesto. | F15: Administrador del cliente | G15: plat.perfil.gestionar | H15: Existen roles activos de los productos contratados. | I15: 1. El actor crea el perfil con código y nombre. 2. Selecciona uno o más roles de los productos contratados. 3. El sistema guarda el perfil y recalcula permisos de los usuarios que lo tienen asignado. | J15: codigo (texto 3-50, único por tenant); nombre (texto 3-100); roles[] (uuid de roles activos) | K15: TR-RN-007 | L15: Perfil disponible para asignación | M15: Should | N15: MVP | O15: TR-P02 | P15: TR-SEG | Q15: TR-RNF-101, TR-RNF-027 | R15: No | S15: =COUNTIF('Criterios GWT'!B:B,A15) -> 2
... A20: TR-RF-017 | B20: MOD-02 · Seguridad y accesos (TR-SEG) | C20: APP-03 · API de servicios de plataforma | D20: Exigir MFA para permisos sensibles | E20: El sistema debe exigir autenticación multifactor reciente (máximo 15 minutos) antes de ejecutar cualquier acción cuyo permiso esté marcado como sensible, solicitando la elevación al IdP cuando no esté vigente. | F20: Usuario operativo del producto, Proveedor de identidad OIDC (IdP) | G20: plat.mfa.elevar | H20: El permiso requerido tiene sensible = true en el manifiesto. | I20: 1. El guard detecta que la acción requiere un permiso sensible. 2. Verifica el claim de hora de MFA (amr/auth_time) del token. 3. Si supera 15 minutos, responde 401 con el desafío step-up. 4. El shell redirige al IdP para el segundo factor y reintenta la acción con el nuevo token. 5. La acción ejecutada se audita con indicador de MFA. | J20: permiso (código sensible); auth_time (epoch del IdP); amr (incluye otp o webauthn) | K20: TR-RN-009 | L20: Acción ejecutada con MFA vigente o rechazada con desafío | M20: Must | N20: MVP | O20: TR-P02 | P20: TR-SEG, TR-AUD | Q20: TR-RNF-009, TR-RNF-013 | R20: No | S20: =COUNTIF('Criterios GWT'!B:B,A20) -> 2
A21: TR-RF-018 | B21: MOD-02 · Seguridad y accesos (TR-SEG) | C21: APP-02 · Administración del cliente (embebible) | D21: Gestionar sesiones activas | E21: El sistema debe permitir al administrador del cliente ver las sesiones activas de los usuarios de su tenant (dispositivo, IP, último uso) y cerrarlas de forma remota, y al usuario ver y cerrar las propias. | F21: Administrador del cliente, Usuario operativo del producto | G21: plat.sesion.gestionar | H21: El IdP expone la gestión de sesiones del realm o proyecto. | I21: 1. El actor abre la lista de sesiones filtrada por usuario o sucursal. 2. El sistema consulta al IdP y la enriquece con el último contexto de sucursal. 3. El actor selecciona una sesión y la cierra. 4. El sistema revoca los tokens de renovación y registra el evento. | J21: usuario (texto); dispositivo (texto); ip (inet); inicio (fecha-hora); ultimo_uso (fecha-hora); sucursal (texto) | L21: Sesión cerrada y usuario obligado a autenticarse nuevamente | M21: Should | N21: R2 | O21: TR-P02 | P21: TR-SEG, TR-AUD | Q21: TR-RNF-014, TR-RNF-013 | R21: No | S21: =COUNTIF('Criterios GWT'!B:B,A21) -> 2
A22: TR-RF-019 | B22: MOD-02 · Seguridad y accesos (TR-SEG) | C22: APP-02 · Administración del cliente (embebible) | D22: Consultar bitácora de seguridad | E22: El sistema debe permitir consultar la bitácora de eventos de seguridad del tenant (inicios de sesión, accesos denegados, asignaciones otorgadas o revocadas, accesos de soporte) con filtros y exportación. | F22: Administrador del cliente, Responsable de datos personales del cliente | G22: plat.seguridad.bitacora | H22: Existen eventos en seg.evento_seguridad para el tenant. | I22: 1. El actor define filtros de fecha, usuario y tipo de evento. 2. El sistema devuelve la lista paginada ordenada por fecha descendente. 3. El actor abre el detalle con IP y datos del evento o exporta a Excel. | J22: fecha_desde, fecha_hasta (fecha); usuario (texto); tipo (LOGIN|ACCESO_DENEGADO|ASIGNACION_OTORGADA|ASIGNACION_REVOCADA|ACCESO_SOPORTE) | K22: TR-RN-047 | L22: Listado paginado de eventos y exportación auditada | M22: Should | N22: MVP | O22: TR-P02, TR-P11 | P22: TR-SEG, TR-AUD, TR-REP | Q22: TR-RNF-002, TR-RNF-013 | R22: No | S22: =COUNTIF('Criterios GWT'!B:B,A22) -> 2
A23: TR-RF-020 | B23: MOD-02 · Seguridad y accesos (TR-SEG) | C23: APP-02 · Administración del cliente (embebible) | D23: Autorizar acceso temporal de soporte | E23: El sistema debe permitir al administrador del cliente autorizar que un agente de soporte acceda a su tenant con motivo, ticket asociado, alcance y vigencia máxima de 4 horas, y al agente operar con un banner visible y auditoría de cada acción. | F23: Administrador del cliente, Agente de soporte (N1/N2) | G23: plat.soporte.autorizar | H23: Existe un ticket abierto del tenant asignado al agente. | I23: 1. El agente solicita acceso desde el ticket indicando motivo y alcance de solo lectura o lectura y escritura. 2. El administrador del cliente recibe la solicitud y la aprueba con vigencia de hasta 4 horas. 3. El sistema crea una membresía temporal tipo SOPORTE y registra ACCESO_SOPORTE. 4. El agente opera con un banner «Sesión de soporte»; cada acción se audita con el número de ticket. 5. Al vencer la vigencia o cerrar el ticket, el acceso se revoca automáticamente. | J23: ticket (SOP-######); motivo (texto 10-300); modo (LECTURA|ESCRITURA); vigencia_horas (1-4); aprobado_por (uuid) | K23: TR-RN-011 | L23: Acceso de soporte vigente, visible y auditado, revocado automáticamente | M23: Must | N23: MVP | O23: TR-P02, TR-P08 | P23: TR-SEG, TR-SOP, TR-AUD, TR-NOT | Q23: TR-RNF-110, TR-RNF-013 | R23: No | S23: =COUNTIF('Criterios GWT'!B:B,A23) -> 3
A24: TR-RF-021 | B24: MOD-02 · Seguridad y accesos (TR-SEG) | C24: APP-02 · Administración del cliente (embebible) | D24: Transferir propiedad del tenant | E24: El sistema debe permitir al propietario transferir la propiedad del tenant a otro miembro activo, con confirmación por MFA de ambos, conservando la trazabilidad. | F24: Administrador del cliente | G24: plat.tenant.transferir | H24: El destinatario es miembro ACTIVO del tenant. | I24: 1. El propietario selecciona al nuevo propietario y confirma con MFA. 2. El sistema notifica al destinatario, que acepta con MFA. 3. El sistema marca al destinatario como propietario y, si se indicó, retira la marca al anterior. 4. Registra el cambio en auditoría y notifica a ambos. | J24: nuevo_propietario_id (uuid); conservar_propiedad_actual (booleano); motivo (texto 5-300) | K24: TR-RN-010, TR-RN-009 | L24: Propiedad transferida con aceptación del destinatario | M24: Could | N24: R2 | O24: TR-P01, TR-P02 | P24: TR-SEG, TR-AUD, TR-NOT | Q24: TR-RNF-009, TR-RNF-021 | R24: No | S24: =COUNTIF('Criterios GWT'!B:B,A24) -> 2
A25: TR-RF-022 | B25: MOD-03 · Catálogos y tablas maestras (TR-CAT) | C25: APP-01 · Consola de plataforma | D25: Administrar catálogos globales | E25: El sistema debe permitir al administrador de plataforma crear y editar la definición de catálogos (código, nombre, alcance GLOBAL, TENANT o MIXTO, fuente y si es editable por el tenant), incrementando la versión ante cada cambio. | F25: Administrador de plataforma | G25: plat.catalogo.gestionar | H25: El actor tiene sesión en la consola de plataforma. | I25: 1. El actor crea o edita un catálogo. 2. El sistema valida unicidad del código y coherencia entre alcance y editable_por_tenant. 3. Guarda, incrementa la versión y publica catalogo.actualizado. 4. El sistema invalida la caché del catálogo en Redis. | J25: codigo (texto 3-60, mayúsculas y guion bajo, único); nombre (texto 3-150); alcance (GLOBAL|TENANT|MIXTO); fuente (texto 0-150, p. ej. «SUNAT Catálogo 06»); editable_por_tenant (booleano); version (entero autoincremental) | K25: TR-RN-012 | L25: Catálogo definido y versionado | M25: Must | N25: MVP | O25: TR-P03 | P25: TR-CAT, TR-EVT | Q25: TR-RNF-102, TR-RNF-027 | R25: No | S25: =COUNTIF('Criterios GWT'!B:B,A25) -> 2
A26: TR-RF-023 | B26: MOD-03 · Catálogos y tablas maestras (TR-CAT) | C26: APP-01 · Consola de plataforma | D26: Administrar ítems de catálogo con vigencia | E26: El sistema debe permitir registrar, editar, inactivar y cerrar la vigencia de ítems de un catálogo con código, código externo oficial, nombre, abreviatura, orden y atributos JSON, sin eliminar ítems referenciados. | F26: Administrador de plataforma, Administrador del cliente | G26: plat.catalogo.item_gestionar | H26: El catálogo existe; para ítems propios del tenant el catálogo es MIXTO o TENANT. | I26: 1. El actor abre el catálogo y agrega o edita un ítem. 2. Ingresa código, código externo, nombre, orden, atributos y vigencia. 3. El sistema valida unicidad por catálogo y tenant (TR-RN-013). 4. Ante eliminación de ítem referenciado, el sistema ofrece cerrar la vigencia. 5. Guarda, incrementa la versión del catálogo e invalida la caché. | J26: codigo (texto 1-40); codigo_externo (texto 0-40); nombre (texto 1-200); abreviatura (0-30); orden (entero); atributos (JSON: longitud, regex, valida_reniec, mascara); vigente_desde (fecha); vigente_hasta (fecha opcional ≥ desde); activo (booleano) | K26: TR-RN-012, TR-RN-013 | L26: Ítem vigente o cerrado sin pérdida de referencias | M26: Must | N26: MVP | O26: TR-P03 | P26: TR-CAT, TR-EVT | Q26: TR-RNF-102, TR-RNF-021 | R26: No | S26: =COUNTIF('Criterios GWT'!B:B,A26) -> 3
A27: TR-RF-024 | B27: MOD-03 · Catálogos y tablas maestras (TR-CAT) | C27: APP-03 · API de servicios de plataforma | D27: Consultar ítems de catálogo con caché | E27: El sistema debe exponer GET /v1/catalogos/{codigo}/items que devuelva los ítems vigentes y visibles para el tenant (globales más propios con ajustes aplicados), con ETag, caché Redis y respuesta 304 cuando no hay cambios. | F27: Módulo de producto consumidor, Usuario operativo del producto | G27: plat.catalogo.leer | H27: El request tiene contexto de tenant. | I27: 1. El cliente solicita los ítems con If-None-Match opcional. 2. El sistema busca en Redis la clave cat:{codigo}:{tenant}:{version}. 3. Si no existe, ejecuta cat.items y guarda el resultado con TTL. 4. Devuelve 200 con ETag o 304 si coincide. | J27: codigo (ruta); If-None-Match (cabecera opcional); respuesta: item_id, codigo, codigo_externo, nombre (alias si existe), atributos, orden | K27: TR-RN-012 | L27: Lista ordenada de ítems vigentes o 304 | M27: Must | N27: MVP | O27: TR-P03 | P27: TR-CAT | Q27: TR-RNF-102, TR-RNF-002 | R27: No | S27: =COUNTIF('Criterios GWT'!B:B,A27) -> 3
A28: TR-RF-025 | B28: MOD-03 · Catálogos y tablas maestras (TR-CAT) | C28: APP-02 · Administración del cliente (embebible) | D28: Personalizar ítems globales por tenant | E28: El sistema debe permitir al administrador del cliente ocultar, reordenar y renombrar (alias) ítems globales de catálogos MIXTO sin alterar el ítem global ni afectar a otros tenants. | F28: Administrador del cliente | G28: plat.catalogo.personalizar | H28: El catálogo tiene alcance MIXTO o editable_por_tenant = verdadero. | I28: 1. El actor abre el catálogo y ve los ítems globales y propios. 2. Cambia visibilidad, orden o alias de un ítem global. 3. El sistema guarda el ajuste en cat.catalogo_item_tenant e invalida la caché del tenant. | J28: item_id (uuid); visible (booleano); orden (entero opcional); alias (texto 0-200) | K28: TR-RN-012 | L28: Lista del tenant con ajustes aplicados | M28: Should | N28: MVP | O28: TR-P03 | P28: TR-CAT | Q28: TR-RNF-027, TR-RNF-102 | R28: No | S28: =COUNTIF('Criterios GWT'!B:B,A28) -> 2
A29: TR-RF-026 | B29: MOD-03 · Catálogos y tablas maestras (TR-CAT) | C29: APP-02 · Administración del cliente (embebible) | D29: Registrar ítems propios del tenant | E29: El sistema debe permitir al administrador del cliente registrar, editar e inactivar ítems propios en catálogos MIXTO o TENANT (por ejemplo especialidades, categorías de producto, tipos de trámite). | F29: Administrador del cliente | G29: plat.catalogo.item_propio | H29: El catálogo es MIXTO o TENANT. | I29: 1. El actor agrega un ítem con código y nombre. 2. El sistema valida que el código no coincida con un ítem global ni propio existente. 3. Guarda con tenant_id del contexto e invalida la caché. | J29: codigo (texto 1-40); nombre (texto 1-200); orden (entero); atributos (JSON opcional); activo (booleano) | K29: TR-RN-012, TR-RN-013 | L29: Ítem propio disponible solo para el tenant | M29: Must | N29: MVP | O29: TR-P03 | P29: TR-CAT | Q29: TR-RNF-027, TR-RNF-010 | R29: No | S29: =COUNTIF('Criterios GWT'!B:B,A29) -> 2
A30: TR-RF-027 | B30: MOD-03 · Catálogos y tablas maestras (TR-CAT) | C30: APP-03 · API de servicios de plataforma | D30: Validar valor contra catálogo | E30: El sistema debe proveer el puerto CatalogoPort.validarItem(catalogo, codigo) que confirme si un código es vigente y visible para el tenant y devuelva sus atributos para validaciones del producto. | F30: Módulo de producto consumidor | G30: plat.catalogo.leer | H30: El módulo de producto tiene contexto de tenant. | I30: 1. El módulo invoca validarItem con catálogo y código. 2. El sistema resuelve desde caché los ítems del tenant. 3. Devuelve válido con atributos o inválido con motivo (inexistente, inactivo, fuera de vigencia, oculto). | J30: catalogo (texto); codigo (texto); respuesta: valido (booleano), motivo (texto), atributos (JSON) | K30: TR-RN-012, TR-RN-013 | L30: Resultado de validación con atributos | M30: Must | N30: MVP | O30: TR-P03, TR-P10 | P30: TR-CAT | Q30: TR-RNF-102, TR-RNF-012 | R30: No | S30: =COUNTIF('Criterios GWT'!B:B,A30) -> 2
A31: TR-RF-028 | B31: MOD-03 · Catálogos y tablas maestras (TR-CAT) | C31: APP-01 · Consola de plataforma | D31: Importar tablas maestras oficiales | E31: El sistema debe permitir importar nuevas versiones de tablas oficiales (ubigeo INEI, CIE-10, catálogos SUNAT 01, 03, 06, 07, monedas ISO 4217) desde archivo CSV o Excel con previsualización de altas, cambios y bajas antes de aplicar. | F31: Administrador de plataforma | G31: plat.catalogo.importar | H31: El actor dispone del archivo oficial con la estructura de la plantilla. | I31: 1. El actor elige la tabla y sube el archivo. 2. El sistema almacena el archivo en TR-ARC y valida estructura y codificación UTF-8. 3. Muestra el resumen de altas, modificaciones y ítems a cerrar. 4. El actor confirma y el sistema aplica en una transacción, cierra vigencias de bajas y publica catalogo.actualizado. | J31: tabla (UBIGEO|CIE10|TIPO_COMPROBANTE|UNIDAD_MEDIDA|TIPO_DOC_IDENTIDAD|AFECTACION_IGV|MONEDA); archivo (CSV/XLSX ≤ 20 MB); version_oficial (texto); fecha_vigencia (fecha) | K31: TR-RN-012, TR-RN-013, TR-RN-027 | L31: Tabla actualizada con versión registrada y resumen de cambios | M31: Must | N31: MVP | O31: TR-P03 | P31: TR-CAT, TR-ARC, TR-EVT, TR-AUD | Q31: TR-RNF-017, TR-RNF-013 | R31: No | S31: =COUNTIF('Criterios GWT'!B:B,A31) -> 3
A32: TR-RF-029 | B32: MOD-03 · Catálogos y tablas maestras (TR-CAT) | C32: APP-02 · Administración del cliente (embebible) | D32: Gestionar feriados y calcular días hábiles | E32: El sistema debe mantener feriados nacionales (globales) y días no laborables propios del tenant o sucursal, y proveer el servicio de cálculo de días hábiles (sumar y contar días hábiles) usado por plazos de ARCO, expedientes y SLA. | F32: Administrador de plataforma, Administrador del cliente, Módulo de producto consumidor | G32: plat.feriado.gestionar | H32: El catálogo FERIADO existe con alcance MIXTO. | I32: 1. El administrador de plataforma registra los feriados nacionales del año. 2. El administrador del cliente registra días no laborables propios con alcance tenant o sucursal. 3. Un módulo invoca CalendarioPort.sumarDiasHabiles(fecha, n, sucursal). 4. El sistema excluye sábados y domingos según parámetro, feriados nacionales y propios, y devuelve la fecha resultante. | J32: fecha (fecha); nombre (texto 3-100); alcance (GLOBAL|TENANT|SUCURSAL); sucursal_id (uuid opcional); recurrente_anual (booleano); sabado_habil (parámetro BOOLEANO) | K32: TR-RN-012, TR-RN-014 | L32: Fecha de vencimiento en días hábiles calculada de forma consistente | M32: Must | N32: MVP | O32: TR-P03, TR-P11 | P32: TR-CAT, TR-CFG | Q32: TR-RNF-027, TR-RNF-002 | R32: No | S32: =COUNTIF('Criterios GWT'!B:B,A32) -> 3
A33: TR-RF-030 | B33: MOD-04 · Parámetros jerárquicos (TR-CFG) | C33: APP-03 · API de servicios de plataforma | D33: Registrar definiciones de parámetros | E33: El sistema debe registrar desde el manifiesto de cada producto las definiciones de parámetros con código, tipo, valor por defecto, descripción y alcance máximo, sin perder los valores configurados por los tenants. | F33: Planificador de tareas, Administrador de plataforma | G33: plat.parametro.definir | H33: Se aplica el manifiesto del producto. | I33: 1. El proceso de manifiesto envía las definiciones. 2. El sistema valida el código (producto.ambito.nombre) y que el valor por defecto corresponda al tipo. 3. Inserta las nuevas y actualiza descripción o defecto de las existentes. 4. Las definiciones retiradas se marcan obsoletas conservando valores. | J33: codigo (texto 3-80); producto_codigo (5); descripcion (texto 3-250); tipo (TEXTO|NUMERO|BOOLEANO|JSON); valor_defecto (JSON); alcance_maximo (TENANT|EMPRESA|SUCURSAL); esquema (JSON Schema opcional) | K33: TR-RN-015 | L33: Definiciones vigentes en cfg.parametro_def | M33: Must | N33: MVP | O33: TR-P03 | P33: TR-CFG, TR-SEG | Q33: TR-RNF-120, TR-RNF-027 | R33: No | S33: =COUNTIF('Criterios GWT'!B:B,A33) -> 2
... A141: TR-RF-138 | B141: MOD-21 · Agente local (TR-EDGE) | C141: APP-01 · Consola de plataforma | D141: Monitorear y actualizar agentes de forma remota | E141: El sistema debe recibir el latido (heartbeat) de cada agente con versión, estado de dispositivos y tamaño de cola, mostrar su estado en la consola, alertar cuando un agente deje de reportar y distribuir actualizaciones firmadas por anillos (piloto y general). | F141: Administrador de plataforma, Agente de soporte (N1/N2), Planificador de tareas | G141: plat.edge.gestionar | H141: Existen agentes enrolados. | I141: 1. El agente envía un latido cada 60 segundos. 2. El sistema actualiza su estado y registra métricas en TR-OBS. 3. Si no recibe latido en 5 minutos en horario de operación, abre una alerta SIN_DATOS. 4. El administrador publica una nueva versión para el anillo piloto y luego general. 5. El agente descarga, verifica la firma e instala fuera del horario de operación. | J141: agente_id; version; dispositivos[] (tipo IMPRESORA|CAJON|BIOMETRICO|KIOSCO|PANTALLA, estado); cola_pendiente (entero); ultimo_latido; anillo (PILOTO|GENERAL) | K141: TR-RN-046 | L141: Parque de agentes visible y actualizado | M141: Should | N141: R2 | O141: TR-P09, TR-P12 | P141: TR-EDGE, TR-OBS, TR-SOP | Q141: TR-RNF-108, TR-RNF-127 | R141: No | S141: =COUNTIF('Criterios GWT'!B:B,A141) -> 3

Sheet Criterios GWT
A1: Criterios de aceptación — formato GWT atómico
A2: DADO QUE [contexto] · CUANDO [acción] · ENTONCES [resultado verificable]. Completar Estado de prueba y Observaciones.
A3: ID | B3: RF | C3: Requerimiento | D3: Escenario | E3: Tipo | F3: DADO QUE | G3: CUANDO | H3: ENTONCES | I3: Estado de prueba | J3: Observaciones
A4: TR-CA-001 | B4: TR-RF-001 | C4: Dar de alta un tenant con asistente | D4: Alta completa en modalidad prueba | E4: Positivo | F4: DADO QUE el administrador de plataforma tiene el permiso plat.tenant.crear y no existe el código «polleria-dona-rosa» | G4: CUANDO completa el asistente con producto REST, plan BASICO, modalidad PRUEBA y RUC 20601234561 | H4: ENTONCES se crea el tenant «polleria-dona-rosa» en estado PRUEBA con su sucursal principal 0000 y se envía la invitación al propietario | I4: Pendiente
A5: TR-CA-002 | B5: TR-RF-001 | C5: Dar de alta un tenant con asistente | D5: Código de tenant duplicado | E5: Negativo | F5: DADO QUE existe el tenant con código «polleria-dona-rosa» | G5: CUANDO intenta crear otro tenant con el mismo código | H5: ENTONCES el sistema rechaza el alta con el mensaje «El código de tenant ya existe» y no crea ningún registro | I5: Pendiente
A6: TR-CA-003 | B6: TR-RF-001 | C6: Dar de alta un tenant con asistente | D6: RUC con dígito verificador inválido | E6: Negativo | F6: DADO QUE el administrador está en el paso de empresa del asistente | G6: CUANDO ingresa el RUC 20601234560 | H6: ENTONCES el sistema muestra «RUC inválido» y no permite avanzar al siguiente paso | I6: Pendiente
A7: TR-CA-004 | B7: TR-RF-002 | C7: Registrar empresa del tenant | D7: Registro con datos del padrón | E7: Positivo | F7: DADO QUE el administrador del cliente tiene alcance TENANT en «grupo-sabores» | G7: CUANDO registra la empresa con RUC 20512345678 | H7: ENTONCES la empresa queda activa con la razón social devuelta por el padrón y su sucursal principal 0000 | I7: Pendiente
A8: TR-CA-005 | B8: TR-RF-002 | C8: Registrar empresa del tenant | D8: RUC ya registrado en el tenant | E8: Negativo | F8: DADO QUE la empresa con RUC 20512345678 ya existe en el tenant | G8: CUANDO intenta registrarla nuevamente | H8: ENTONCES el sistema rechaza la operación con «La empresa ya está registrada en este tenant» | I8: Pendiente
A9: TR-CA-006 | B9: TR-RF-002 | C9: Registrar empresa del tenant | D9: Contribuyente no habido | E9: Borde | F9: DADO QUE el padrón devuelve condición NO HABIDO para el RUC 20498765432 | G9: CUANDO el actor confirma el registro | H9: ENTONCES el sistema registra la empresa y muestra la advertencia «Contribuyente NO HABIDO: no podrá emitir comprobantes hasta regularizar» | I9: Pendiente
A10: TR-CA-007 | B10: TR-RF-003 | C10: Registrar sucursal (establecimiento) | D10: Nueva sucursal en Arequipa | E10: Positivo | F10: DADO QUE la empresa «Sabores del Sur SAC» tiene 1 sucursal y su plan permite 3 | G10: CUANDO registra la sucursal «Cayma» con establecimiento 0002 y ubigeo 040103 | H10: ENTONCES la sucursal «Cayma» queda activa y aparece en el selector de sucursales | I10: Pendiente
A11: TR-CA-008 | B11: TR-RF-003 | C11: Registrar sucursal (establecimiento) | D11: Límite de sucursales del plan | E11: Negativo | F11: DADO QUE la suscripción REST del tenant tiene limite_sucursales = 2 y ya existen 2 sucursales activas | G11: CUANDO intenta registrar una tercera sucursal | H11: ENTONCES el sistema rechaza con «Su plan permite 2 sucursales; amplíe su plan» | I11: Pendiente
A12: TR-CA-009 | B12: TR-RF-003 | C12: Registrar sucursal (establecimiento) | D12: Segunda sucursal principal | E12: Borde | F12: DADO QUE la empresa ya tiene la sucursal principal «Centro» | G12: CUANDO marca como principal la sucursal «Cayma» | H12: ENTONCES el sistema traslada la marca de principal a «Cayma» y la retira de «Centro» en la misma operación | I12: Pendiente
A13: TR-CA-010 | B13: TR-RF-004 | C13: Registrar unidad operativa | D13: Caja en sucursal | E13: Positivo | F13: DADO QUE la sucursal «Cayma» existe | G13: CUANDO registra la unidad tipo CAJA con código «CAJA-01» | H13: ENTONCES la unidad «CAJA-01» queda activa en la sucursal «Cayma» | I13: Pendiente
A14: TR-CA-011 | B14: TR-RF-004 | C14: Registrar unidad operativa | D14: Consultorio sin sucursal | E14: Negativo | F14: DADO QUE el actor no selecciona sucursal | G14: CUANDO intenta registrar una unidad tipo CONSULTORIO | H14: ENTONCES el sistema rechaza con «Solo los almacenes pueden registrarse sin sucursal» | I14: Pendiente
A15: TR-CA-012 | B15: TR-RF-004 | C15: Registrar unidad operativa | D15: Almacén central de empresa | E15: Borde | F15: DADO QUE la empresa «Librería Amauta EIRL» existe | G15: CUANDO registra una unidad tipo ALMACEN sin sucursal | H15: ENTONCES el almacén queda registrado a nivel de empresa y visible para todas sus sucursales | I15: Pendiente
... A341: TR-CA-338 | B341: TR-RF-138 | C341: Monitorear y actualizar agentes de forma remota | D341: Agente sin latido | E341: Borde | F341: DADO QUE el agente de «Huancayo» no reporta desde hace 6 minutos en horario de operación | G341: CUANDO se evalúan las reglas | H341: ENTONCES se abre una alerta SIN_DATOS para la sucursal | I341: Pendiente

Sheet RNF
A1: Requerimientos no funcionales (ISO/IEC 25010:2023)
A2: Propios del sistema y heredados de la plataforma (TR-RNF-001…030).
A3: ID | B3: Origen | C3: Característica | D3: Subcaracterística | E3: Descripción | F3: Métrica / umbral | G3: Verificación | H3: Alcance | I3: Prioridad | J3: N.° RF
A4: TR-RNF-001 | B4: Plataforma | C4: Eficiencia de desempeño | D4: Comportamiento temporal | E4: Las operaciones transaccionales de mostrador (registrar venta, cita, ticket, pedido) responden en menos de 800 ms en el percentil 95. | F4: p95 < 800 ms medido en trazas de producción | G4: Prueba de carga (k6) + trazas OpenTelemetry | H4: Todo | I4: Must | J4: =SUMPRODUCT(--ISNUMBER(SEARCH(A4,RF!$Q$4:$Q$141))) -> 9
A5: TR-RNF-002 | B5: Plataforma | C5: Eficiencia de desempeño | D5: Comportamiento temporal | E5: Las consultas y listados paginados responden en menos de 1,5 s en el percentil 95 con hasta 100 000 registros por tenant. | F5: p95 < 1,5 s | G5: Prueba de carga con datos sintéticos | H5: Todo | I5: Must | J5: =SUMPRODUCT(--ISNUMBER(SEARCH(A5,RF!$Q$4:$Q$141))) -> 12
A6: TR-RNF-003 | B6: Plataforma | C6: Eficiencia de desempeño | D6: Capacidad | E6: La plataforma soporta 200 usuarios concurrentes por instancia de API sin degradación mayor al 20 % del p95. | F6: 200 usuarios concurrentes | G6: Prueba de carga escalonada | H6: Todo | I6: Must | J6: =SUMPRODUCT(--ISNUMBER(SEARCH(A6,RF!$Q$4:$Q$141))) -> 0
A7: TR-RNF-004 | B7: Plataforma | C7: Eficiencia de desempeño | D7: Comportamiento temporal | E7: Los portales públicos cumplen Core Web Vitals en móvil: LCP ≤ 2,5 s, INP ≤ 200 ms, CLS ≤ 0,1. | F7: Percentil 75 de usuarios reales | G7: Lighthouse CI + datos de campo | H7: Todo | I7: Must | J7: =SUMPRODUCT(--ISNUMBER(SEARCH(A7,RF!$Q$4:$Q$141))) -> 6
A8: TR-RNF-005 | B8: Plataforma | C8: Fiabilidad | D8: Disponibilidad | E8: Disponibilidad mensual de la API ≥ 99,5 % en el horario comercial del cliente. | F8: ≥ 99,5 % mensual | G8: Monitoreo sintético cada minuto | H8: Todo | I8: Must | J8: =SUMPRODUCT(--ISNUMBER(SEARCH(A8,RF!$Q$4:$Q$141))) -> 4
A9: TR-RNF-006 | B9: Plataforma | C9: Fiabilidad | D9: Recuperabilidad | E9: Respaldo automático diario con retención de 30 días y punto de recuperación ≤ 24 h; restauración en ≤ 4 h. | F9: RPO ≤ 24 h, RTO ≤ 4 h | G9: Prueba de restauración mensual documentada | H9: Todo | I9: Must | J9: =SUMPRODUCT(--ISNUMBER(SEARCH(A9,RF!$Q$4:$Q$141))) -> 1
A10: TR-RNF-007 | B10: Plataforma | C10: Fiabilidad | D10: Tolerancia a fallos | E10: Las integraciones externas (SUNAT/OSE, pasarelas, RENIEC, mensajería) usan timeout, reintento con backoff y circuit breaker; su caída no bloquea la operación principal. | F10: Ninguna operación de mostrador falla por caída de un tercero | G10: Pruebas de caos con dependencias simuladas | H10: Todo | I10: Must | J10: =SUMPRODUCT(--ISNUMBER(SEARCH(A10,RF!$Q$4:$Q$141))) -> 13
A11: TR-RNF-008 | B11: Plataforma | C11: Fiabilidad | D11: Madurez | E11: Las operaciones que cambian estado son idempotentes ante reintentos del cliente mediante clave de idempotencia. | F11: 0 duplicados en pruebas de reintento | G11: Pruebas automatizadas de reintento | H11: Todo | I11: Must | J11: =SUMPRODUCT(--ISNUMBER(SEARCH(A11,RF!$Q$4:$Q$141))) -> 10
A12: TR-RNF-009 | B12: Plataforma | C12: Seguridad | D12: Autenticidad | E12: Autenticación OIDC centralizada; contraseñas gestionadas por el IdP; bloqueo tras 5 intentos fallidos; MFA obligatorio para permisos sensibles. | F12: Configuración verificada | G12: Revisión de configuración + prueba | H12: Todo | I12: Must | J12: =SUMPRODUCT(--ISNUMBER(SEARCH(A12,RF!$Q$4:$Q$141))) -> 8
A13: TR-RNF-010 | B13: Plataforma | C13: Seguridad | D13: Confidencialidad | E13: Aislamiento por tenant con doble barrera: contexto de aplicación y Row Level Security en PostgreSQL. | F13: 0 accesos cruzados en pruebas | G13: Pruebas automatizadas de aislamiento | H13: Todo | I13: Must | J13: =SUMPRODUCT(--ISNUMBER(SEARCH(A13,RF!$Q$4:$Q$141))) -> 11
A14: TR-RNF-011 | B14: Plataforma | C14: Seguridad | D14: Confidencialidad | E14: Cifrado en tránsito TLS 1.2+ y en reposo para base de datos, respaldos y archivos; secretos en gestor de secretos. | F14: 100 % de endpoints con TLS | G14: Escaneo de configuración | H14: Todo | I14: Must | J14: =SUMPRODUCT(--ISNUMBER(SEARCH(A14,RF!$Q$4:$Q$141))) -> 5
A15: TR-RNF-012 | B15: Plataforma | C15: Seguridad | D15: Integridad | E15: Cumplimiento de OWASP ASVS nivel 2 para la API y los frontends; validación de entradas en servidor. | F15: 0 hallazgos altos o críticos abiertos | G15: Análisis SAST/DAST en CI y pentest anual | H15: Todo | I15: Must | J15: =SUMPRODUCT(--ISNUMBER(SEARCH(A15,RF!$Q$4:$Q$141))) -> 3
... A61: TR-RNF-128 | B61: Propio | C61: Protección | D61: Protección contra errores del usuario | E61: El consumo de IA, mensajería y consultas de identidad por tenant tiene límites mensuales con aviso y corte configurable para evitar sobrecostos. | F61: Aviso al 80 % y corte o modo degradado al 100 % según configuración | G61: Prueba funcional con consumo simulado | H61: Todo | I61: Must | J61: =SUMPRODUCT(--ISNUMBER(SEARCH(A61,RF!$Q$4:$Q$141))) -> 3

Sheet Matriz Proceso-RF
A1: Matriz de trazabilidad: procesos × requerimientos funcionales
A2: ● = el RF soporta el proceso. Fila final: total de RF por proceso.
A3: RF | B3: Nombre | C3: Prioridad | D3: TR-P01 | E3: TR-P02 | F3: TR-P03 | G3: TR-P04 | H3: TR-P05 | I3: TR-P06 | J3: TR-P07 | K3: TR-P08 | L3: TR-P09 | M3: TR-P10 | N3: TR-P11 | O3: TR-P12 | P3: TR-P13
A4: TR-RF-001 | B4: Dar de alta un tenant con asistente | C4: Must | D4: ●
A5: TR-RF-002 | B5: Registrar empresa del tenant | C5: Must | D5: ● | M5: ●
A6: TR-RF-003 | B6: Registrar sucursal (establecimiento) | C6: Must | D6: ●
A7: TR-RF-004 | B7: Registrar unidad operativa | C7: Must | D7: ●
A8: TR-RF-005 | B8: Gestionar suscripción de producto | C8: Must | D8: ● | H8: ●
A9: TR-RF-006 | B9: Cambiar estado del tenant | C9: Must | D9: ● | H9: ●
A10: TR-RF-007 | B10: Controlar vencimiento de prueba y suscripción | C10: Must | D10: ● | H10: ●
A11: TR-RF-008 | B11: Aplicar manifiesto funcional del producto | C11: Must | E11: ● | F11: ●
A12: TR-RF-009 | B12: Invitar usuario al tenant | C12: Must | E12: ●
A13: TR-RF-010 | B13: Aceptar invitación y vincular identidad | C13: Must | E13: ●
A14: TR-RF-011 | B14: Gestionar roles propios del tenant | C14: Must | E14: ●
A15: TR-RF-012 | B15: Gestionar perfiles de puesto | C15: Should | E15: ●
A16: TR-RF-013 | B16: Asignar rol o perfil con alcance y vigencia | C16: Must | E16: ●
A17: TR-RF-014 | B17: Revocar acceso y suspender membresía | C17: Must | E17: ●
A18: TR-RF-015 | B18: Calcular permisos efectivos y menú | C18: Must | E18: ●
A19: TR-RF-016 | B19: Seleccionar empresa y sucursal de trabajo | C19: Must | E19: ●
A20: TR-RF-017 | B20: Exigir MFA para permisos sensibles | C20: Must | E20: ●
A21: TR-RF-018 | B21: Gestionar sesiones activas | C21: Should | E21: ●
A22: TR-RF-019 | B22: Consultar bitácora de seguridad | C22: Should | E22: ● | N22: ●
A23: TR-RF-020 | B23: Autorizar acceso temporal de soporte | C23: Must | E23: ● | K23: ●
A24: TR-RF-021 | B24: Transferir propiedad del tenant | C24: Could | D24: ● | E24: ●
A25: TR-RF-022 | B25: Administrar catálogos globales | C25: Must | F25: ●
A26: TR-RF-023 | B26: Administrar ítems de catálogo con vigencia | C26: Must | F26: ●
A27: TR-RF-024 | B27: Consultar ítems de catálogo con caché | C27: Must | F27: ●
A28: TR-RF-025 | B28: Personalizar ítems globales por tenant | C28: Should | F28: ●
A29: TR-RF-026 | B29: Registrar ítems propios del tenant | C29: Must | F29: ●
A30: TR-RF-027 | B30: Validar valor contra catálogo | C30: Must | F30: ● | M30: ●
A31: TR-RF-028 | B31: Importar tablas maestras oficiales | C31: Must | F31: ●
A32: TR-RF-029 | B32: Gestionar feriados y calcular días hábiles | C32: Must | F32: ● | N32: ●
A33: TR-RF-030 | B33: Registrar definiciones de parámetros | C33: Must | F33: ●
A34: TR-RF-031 | B34: Configurar valor de parámetro por alcance | C34: Must | F34: ●
A35: TR-RF-032 | B35: Resolver valor efectivo de parámetro | C35: Must | F35: ●
A36: TR-RF-033 | B36: Ver herencia y restablecer parámetro | C36: Should | F36: ●
A37: TR-RF-034 | B37: Consultar historial de cambios de parámetros | C37: Should | F37: ● | N37: ●
A38: TR-RF-035 | B38: Configurar series y correlativos | C38: Must | F38: ● | G38: ●
A39: TR-RF-036 | B39: Obtener siguiente número atómico | C39: Must | F39: ● | G39: ●
A40: TR-RF-037 | B40: Reiniciar correlativo por periodo | C40: Must | F40: ● | O40: ●
A41: TR-RF-038 | B41: Reservar bloques de numeración para operación offline | C41: Should | F41: ● | O41: ●
A42: TR-RF-039 | B42: Registrar persona con documento | C42: Must | M42: ●
A43: TR-RF-040 | B43: Asignar rol de persona por producto | C43: Must | M43: ●
A44: TR-RF-041 | B44: Gestionar contactos y direcciones | C44: Must | M44: ●
A45: TR-RF-042 | B45: Detectar y fusionar personas duplicadas | C45: Should | M45: ●
A46: TR-RF-043 | B46: Registrar consentimientos de la persona | C46: Must | M46: ● | N46: ●
A47: TR-RF-044 | B47: Validar formato de DNI y RUC | C47: Must | M47: ●
A48: TR-RF-045 | B48: Consultar DNI con caché y proveedor | C48: Must | M48: ●
A49: TR-RF-046 | B49: Consultar RUC con estado y condición | C49: Must | G49: ● | M49: ●
A50: TR-RF-047 | B50: Controlar cuota de consultas por plan | C50: Must | D50: ● | M50: ●
A51: TR-RF-048 | B51: Solicitar autorización de identidad portable | C51: Should | M51: ● | N51: ●
A52: TR-RF-049 | B52: Confirmar autorización con código | C52: Should | M52: ● | N52: ●
A53: TR-RF-050 | B53: Entregar datos autorizados y registrar acceso | C53: Should | M53: ●
A54: TR-RF-051 | B54: Revocar autorizaciones y ver accesos del titular | C54: Should | M54: ● | N54: ●
A55: TR-RF-052 | B55: Configurar emisor electrónico | C55: Must | D55: ● | G55: ●
A56: TR-RF-053 | B56: Emitir factura electrónica | C56: Must | G56: ●
A57: TR-RF-054 | B57: Emitir boleta de venta electrónica | C57: Must | G57: ●
A58: TR-RF-055 | B58: Emitir nota de crédito | C58: Must | G58: ● | H58: ●
A59: TR-RF-056 | B59: Emitir nota de débito | C59: Should | G59: ●
A60: TR-RF-057 | B60: Enviar resumen diario de boletas | C60: Must | G60: ●
A61: TR-RF-058 | B61: Comunicar baja de comprobantes | C61: Must | G61: ●
A62: TR-RF-059 | B62: Procesar respuesta y CDR del OSE | C62: Must | G62: ●
A63: TR-RF-060 | B63: Reintentar envíos y operar en contingencia | C63: Must | G63: ● | L63: ●
A64: TR-RF-061 | B64: Generar representación impresa | C64: Must | G64: ●
A65: TR-RF-062 | B65: Entregar comprobante al cliente | C65: Should | G65: ● | I65: ●
A66: TR-RF-063 | B66: Monitorear comprobantes pendientes y rechazados | C66: Must | G66: ● | P66: ●
A67: TR-RF-064 | B67: Exportar registro de ventas electrónico | C67: Could | G67: ● | P67: ●
A68: TR-RF-065 | B68: Configurar pasarela de pagos por empresa | C68: Must | H68: ●
A69: TR-RF-066 | B69: Crear intención de cobro con tarjeta | C69: Must | H69: ●
A70: TR-RF-067 | B70: Cobrar con Yape o Plin | C70: Must | H70: ●
A71: TR-RF-068 | B71: Generar link de pago | C71: Should | H71: ● | I71: ●
A72: TR-RF-069 | B72: Procesar webhook de la pasarela | C72: Must | H72: ●
A73: TR-RF-070 | B73: Reembolsar pago | C73: Must | H73: ●
A74: TR-RF-071 | B74: Gestionar cobros recurrentes | C74: Should | H74: ●
A75: TR-RF-072 | B75: Conciliar liquidaciones de la pasarela | C75: Must | H75: ● | P75: ●
A76: TR-RF-073 | B76: Facturar y cobrar la suscripción del tenant | C76: Must | D76: ● | H76: ●
A77: TR-RF-074 | B77: Gestionar plantillas de notificación | C77: Must | I77: ●
A78: TR-RF-075 | B78: Enviar notificación transaccional | C78: Must | I78: ●
A79: TR-RF-076 | B79: Programar recordatorios | C79: Must | I79: ●
A80: TR-RF-077 | B80: Gestionar preferencias y bajas del destinatario | C80: Must | I80: ● | N80: ●
A81: TR-RF-078 | B81: Enviar por WhatsApp con plantillas aprobadas | C81: Should | I81: ●
A82: TR-RF-079 | B82: Registrar estado de entrega y conmutar canal | C82: Must | I82: ●
A83: TR-RF-080 | B83: Subir archivo validado | C83: Must | J83: ● | N83: ●
A84: TR-RF-081 | B84: Versionar archivo | C84: Should | N84: ●
A85: TR-RF-082 | B85: Descargar archivo con URL firmada | C85: Must | N85: ●
A86: TR-RF-083 | B86: Aplicar retención y bloqueo legal de archivos | C86: Should | G86: ● | N86: ●
A87: TR-RF-084 | B87: Registrar evento de auditoría inmutable | C87: Must | N87: ●
A88: TR-RF-085 | B88: Registrar acceso a datos sensibles | C88: Must | N88: ●
A89: TR-RF-086 | B89: Consultar y exportar auditoría | C89: Must | N89: ●
A90: TR-RF-087 | B90: Verificar integridad de la auditoría | C90: Should | L90: ● | N90: ●
A91: TR-RF-088 | B91: Registrar solicitud de derechos ARCO | C91: Must | N91: ●
A92: TR-RF-089 | B92: Atender solicitud ARCO | C92: Must | N92: ●
A93: TR-RF-090 | B93: Ejecutar cancelación y anonimización | C93: Must | N93: ●
A94: TR-RF-091 | B94: Registrar y notificar incidente de seguridad de datos | C94: Must | N94: ●
A95: TR-RF-092 | B95: Publicar evento de dominio en el outbox | C95: Must | O95: ●
A96: TR-RF-093 | B96: Despachar eventos a suscriptores internos | C96: Must | L96: ● | O96: ●
A97: TR-RF-094 | B97: Mantener catálogo de eventos y suscripciones | C97: Should | O97: ●
A98: TR-RF-095 | B98: Reprocesar eventos fallidos | C98: Must | L98: ● | O98: ●
A99: TR-RF-096 | B99: Registrar definiciones de reportes | C99: Must | P99: ●
A100: TR-RF-097 | B100: Ejecutar y exportar reporte | C100: Must | P100: ●
...

Sheet Matriz RF-RNF
A1: Matriz de trazabilidad: requerimientos funcionales × no funcionales
A2: Solo las columnas de RNF referenciados por al menos un RF.
A3: RF | B3: Nombre | C3: TR-RNF-001 | D3: TR-RNF-002 | E3: TR-RNF-004 | F3: TR-RNF-005 | G3: TR-RNF-006 | H3: TR-RNF-007 | I3: TR-RNF-008 | J3: TR-RNF-009 | K3: TR-RNF-010 | L3: TR-RNF-011 | M3: TR-RNF-012 | N3: TR-RNF-013 | O3: TR-RNF-014 | P3: TR-RNF-015 | Q3: TR-RNF-016 | R3: TR-RNF-017 | S3: TR-RNF-018 | T3: TR-RNF-019 | U3: TR-RNF-020 | V3: TR-RNF-021 | W3: TR-RNF-022 | X3: TR-RNF-024 | Y3: TR-RNF-026 | Z3: TR-RNF-027 | AA3: TR-RNF-028 | AB3: TR-RNF-029 | AC3: TR-RNF-030 | AD3: TR-RNF-101 | AE3: TR-RNF-102 | AF3: TR-RNF-103 | AG3: TR-RNF-104 | AH3: TR-RNF-105 | AI3: TR-RNF-106 | AJ3: TR-RNF-107 | AK3: TR-RNF-108 | AL3: TR-RNF-109 | AM3: TR-RNF-110 | AN3: TR-RNF-111 | AO3: TR-RNF-112 | AP3: TR-RNF-113 | AQ3: TR-RNF-114 | AR3: TR-RNF-115 | AS3: TR-RNF-116 | AT3: TR-RNF-117 | AU3: TR-RNF-118 | AV3: TR-RNF-119 | AW3: TR-RNF-120 | AX3: TR-RNF-121 | AY3: TR-RNF-122 | AZ3: TR-RNF-123 | BA3: TR-RNF-124 | BB3: TR-RNF-125 | BC3: TR-RNF-126 | BD3: TR-RNF-127 | BE3: TR-RNF-128
A4: TR-RF-001 | B4: Dar de alta un tenant con asistente | I4: ● | K4: ● | AB4: ●
A5: TR-RF-002 | B5: Registrar empresa del tenant | H5: ● | K5: ●
A6: TR-RF-003 | B6: Registrar sucursal (establecimiento) | K6: ● | Z6: ●
A7: TR-RF-004 | B7: Registrar unidad operativa | K7: ● | Z7: ●
A8: TR-RF-005 | B8: Gestionar suscripción de producto | Z8: ● | AD8: ●
A9: TR-RF-006 | B9: Cambiar estado del tenant | N9: ● | V9: ●
A10: TR-RF-007 | B10: Controlar vencimiento de prueba y suscripción | F10: ● | I10: ●
A11: TR-RF-008 | B11: Aplicar manifiesto funcional del producto | X11: ● | AV11: ● | AW11: ●
A12: TR-RF-009 | B12: Invitar usuario al tenant | J12: ● | N12: ●
A13: TR-RF-010 | B13: Aceptar invitación y vincular identidad | J13: ● | O13: ●
A14: TR-RF-011 | B14: Gestionar roles propios del tenant | N14: ● | AD14: ● | AY14: ●
A15: TR-RF-012 | B15: Gestionar perfiles de puesto | Z15: ● | AD15: ●
A16: TR-RF-013 | B16: Asignar rol o perfil con alcance y vigencia | J16: ● | N16: ● | AD16: ●
A17: TR-RF-014 | B17: Revocar acceso y suspender membresía | N17: ● | O17: ● | V17: ●
A18: TR-RF-015 | B18: Calcular permisos efectivos y menú | C18: ● | K18: ● | AD18: ●
A19: TR-RF-016 | B19: Seleccionar empresa y sucursal de trabajo | S19: ● | U19: ● | AD19: ●
A20: TR-RF-017 | B20: Exigir MFA para permisos sensibles | J20: ● | N20: ●
A21: TR-RF-018 | B21: Gestionar sesiones activas | N21: ● | O21: ●
A22: TR-RF-019 | B22: Consultar bitácora de seguridad | D22: ● | N22: ●
A23: TR-RF-020 | B23: Autorizar acceso temporal de soporte | N23: ● | AM23: ●
A24: TR-RF-021 | B24: Transferir propiedad del tenant | J24: ● | V24: ●
A25: TR-RF-022 | B25: Administrar catálogos globales | Z25: ● | AE25: ●
A26: TR-RF-023 | B26: Administrar ítems de catálogo con vigencia | V26: ● | AE26: ●
A27: TR-RF-024 | B27: Consultar ítems de catálogo con caché | D27: ● | AE27: ●
A28: TR-RF-025 | B28: Personalizar ítems globales por tenant | Z28: ● | AE28: ●
A29: TR-RF-026 | B29: Registrar ítems propios del tenant | K29: ● | Z29: ●
A30: TR-RF-027 | B30: Validar valor contra catálogo | M30: ● | AE30: ●
A31: TR-RF-028 | B31: Importar tablas maestras oficiales | N31: ● | R31: ●
A32: TR-RF-029 | B32: Gestionar feriados y calcular días hábiles | D32: ● | Z32: ●
A33: TR-RF-030 | B33: Registrar definiciones de parámetros | Z33: ● | AW33: ●
A34: TR-RF-031 | B34: Configurar valor de parámetro por alcance | N34: ● | Z34: ●
A35: TR-RF-032 | B35: Resolver valor efectivo de parámetro | C35: ● | AD35: ●
A36: TR-RF-033 | B36: Ver herencia y restablecer parámetro | U36: ● | Z36: ●
A37: TR-RF-034 | B37: Consultar historial de cambios de parámetros | D37: ● | N37: ●
A38: TR-RF-035 | B38: Configurar series y correlativos | R38: ● | AF38: ●
A39: TR-RF-036 | B39: Obtener siguiente número atómico | I39: ● | AF39: ●
A40: TR-RF-037 | B40: Reiniciar correlativo por periodo | Y40: ● | AF40: ●
A41: TR-RF-038 | B41: Reservar bloques de numeración para operación offline | AF41: ● | AK41: ●
A42: TR-RF-039 | B42: Registrar persona con documento | C42: ● | K42: ●
A43: TR-RF-040 | B43: Asignar rol de persona por producto | K43: ● | X43: ●
A44: TR-RF-041 | B44: Gestionar contactos y direcciones | M44: ● | S44: ●
A45: TR-RF-042 | B45: Detectar y fusionar personas duplicadas | N45: ● | V45: ●
A46: TR-RF-043 | B46: Registrar consentimientos de la persona | N46: ● | Q46: ●
A47: TR-RF-044 | B47: Validar formato de DNI y RUC | C47: ● | M47: ●
A48: TR-RF-045 | B48: Consultar DNI con caché y proveedor | C48: ● | H48: ● | AN48: ●
A49: TR-RF-046 | B49: Consultar RUC con estado y condición | H49: ● | AN49: ●
A50: TR-RF-047 | B50: Controlar cuota de consultas por plan | H50: ● | BE50: ●
A51: TR-RF-048 | B51: Solicitar autorización de identidad portable | Q51: ● | AN51: ●
A52: TR-RF-049 | B52: Confirmar autorización con código | P52: ● | Q52: ●
A53: TR-RF-050 | B53: Entregar datos autorizados y registrar acceso | N53: ● | Q53: ●
A54: TR-RF-051 | B54: Revocar autorizaciones y ver accesos del titular | Q54: ● | T54: ●
A55: TR-RF-052 | B55: Configurar emisor electrónico | R55: ● | AP55: ●
A56: TR-RF-053 | B56: Emitir factura electrónica | I56: ● | R56: ● | AG56: ●
A57: TR-RF-054 | B57: Emitir boleta de venta electrónica | C57: ● | R57: ●
A58: TR-RF-055 | B58: Emitir nota de crédito | R58: ● | V58: ● | AC58: ●
A59: TR-RF-056 | B59: Emitir nota de débito | R59: ●
A60: TR-RF-057 | B60: Enviar resumen diario de boletas | AG60: ● | AH60: ●
A61: TR-RF-058 | B61: Comunicar baja de comprobantes | R61: ● | V61: ●
A62: TR-RF-059 | B62: Procesar respuesta y CDR del OSE | H62: ● | AG62: ●
A63: TR-RF-060 | B63: Reintentar envíos y operar en contingencia | H63: ● | AH63: ●
A64: TR-RF-061 | B64: Generar representación impresa | C64: ● | R64: ●
A65: TR-RF-062 | B65: Entregar comprobante al cliente | E65: ● | P65: ● | R65: ●
A66: TR-RF-063 | B66: Monitorear comprobantes pendientes y rechazados | D66: ● | AG66: ●
A67: TR-RF-064 | B67: Exportar registro de ventas electrónico | R67: ● | BB67: ●
A68: TR-RF-065 | B68: Configurar pasarela de pagos por empresa | AP68: ● | AX68: ●
A69: TR-RF-066 | B69: Crear intención de cobro con tarjeta | H69: ● | I69: ● | L69: ●
A70: TR-RF-067 | B70: Cobrar con Yape o Plin | C70: ● | H70: ●
A71: TR-RF-068 | B71: Generar link de pago | H71: ● | BA71: ●
A72: TR-RF-069 | B72: Procesar webhook de la pasarela | I72: ● | AL72: ●
A73: TR-RF-070 | B73: Reembolsar pago | J73: ● | V73: ● | AC73: ●
A74: TR-RF-071 | B74: Gestionar cobros recurrentes | H74: ● | I74: ●
A75: TR-RF-072 | B75: Conciliar liquidaciones de la pasarela | D75: ● | BB75: ●
A76: TR-RF-073 | B76: Facturar y cobrar la suscripción del tenant | AG76: ● | BE76: ●
A77: TR-RF-074 | B77: Gestionar plantillas de notificación | U77: ● | Z77: ●
A78: TR-RF-075 | B78: Enviar notificación transaccional | I78: ● | BA78: ●
A79: TR-RF-076 | B79: Programar recordatorios | F79: ● | BA79: ●
A80: TR-RF-077 | B80: Gestionar preferencias y bajas del destinatario | Q80: ● | T80: ●
A81: TR-RF-078 | B81: Enviar por WhatsApp con plantillas aprobadas | AX81: ● | BA81: ●
A82: TR-RF-079 | B82: Registrar estado de entrega y conmutar canal | AL82: ● | BA82: ●
A83: TR-RF-080 | B83: Subir archivo validado | L83: ● | AQ83: ●
A84: TR-RF-081 | B84: Versionar archivo | N84: ● | AQ84: ●
A85: TR-RF-082 | B85: Descargar archivo con URL firmada | K85: ● | AQ85: ●
A86: TR-RF-083 | B86: Aplicar retención y bloqueo legal de archivos | G86: ● | L86: ●
A87: TR-RF-084 | B87: Registrar evento de auditoría inmutable | N87: ● | AO87: ●
A88: TR-RF-085 | B88: Registrar acceso a datos sensibles | N88: ● | Q88: ●
A89: TR-RF-086 | B89: Consultar y exportar auditoría | D89: ● | N89: ●
A90: TR-RF-087 | B90: Verificar integridad de la auditoría | N90: ● | AO90: ●
A91: TR-RF-088 | B91: Registrar solicitud de derechos ARCO | Q91: ● | AS91: ●
A92: TR-RF-089 | B92: Atender solicitud ARCO | Q92: ● | AS92: ●
A93: TR-RF-090 | B93: Ejecutar cancelación y anonimización | Q93: ● | V93: ●
A94: TR-RF-091 | B94: Registrar y notificar incidente de seguridad de datos | N94: ● | Q94: ●
A95: TR-RF-092 | B95: Publicar evento de dominio en el outbox | AI95: ● | AT95: ●
A96: TR-RF-093 | B96: Despachar eventos a suscriptores internos | AA96: ● | AI96: ●
A97: TR-RF-094 | B97: Mantener catálogo de eventos y suscripciones | AT97: ● | AW97: ●
A98: TR-RF-095 | B98: Reprocesar eventos fallidos | Y98: ● | AI98: ●
A99: TR-RF-096 | B99: Registrar definiciones de reportes | K99: ● | AW99: ●
A100: TR-RF-097 | B100: Ejecutar y exportar reporte | D100: ● | BB100: ●
...

Sheet Trazabilidad
A1: Trazabilidad completa (vista plana para el SDD)
A2: Una fila por proceso y RF.
A3: Proceso | B3: Nombre del proceso | C3: RF | D3: Requerimiento | E3: Módulo | F3: Aplicación | G3: Prioridad | H3: Fase | I3: RNF | J3: Criterios | K3: Componentes | L3: Permiso
A4: TR-P01 | B4: Alta y configuración de tenant | C4: TR-RF-001 | D4: Dar de alta un tenant con asistente | E4: MOD-01 | F4: APP-01 | G4: Must | H4: MVP | I4: TR-RNF-029, TR-RNF-010, TR-RNF-008 | J4: TR-CA-001, TR-CA-002, TR-CA-003 | K4: TR-ORG, TR-SEG, TR-IDN, TR-CFG, TR-SEQ, TR-NOT, TR-EVT | L4: plat.tenant.crear
A5: TR-P01 | B5: Alta y configuración de tenant | C5: TR-RF-002 | D5: Registrar empresa del tenant | E5: MOD-01 | F5: APP-02 | G5: Must | H5: MVP | I5: TR-RNF-010, TR-RNF-007 | J5: TR-CA-004, TR-CA-005, TR-CA-006 | K5: TR-ORG, TR-IDN, TR-CAT, TR-EVT | L5: plat.empresa.crear
A6: TR-P01 | B6: Alta y configuración de tenant | C6: TR-RF-003 | D6: Registrar sucursal (establecimiento) | E6: MOD-01 | F6: APP-02 | G6: Must | H6: MVP | I6: TR-RNF-010, TR-RNF-027 | J6: TR-CA-007, TR-CA-008, TR-CA-009 | K6: TR-ORG, TR-CAT, TR-EVT | L6: plat.sucursal.gestionar
A7: TR-P01 | B7: Alta y configuración de tenant | C7: TR-RF-004 | D7: Registrar unidad operativa | E7: MOD-01 | F7: APP-02 | G7: Must | H7: MVP | I7: TR-RNF-010, TR-RNF-027 | J7: TR-CA-010, TR-CA-011, TR-CA-012 | K7: TR-ORG, TR-CAT | L7: plat.unidad.gestionar
A8: TR-P01 | B8: Alta y configuración de tenant | C8: TR-RF-005 | D8: Gestionar suscripción de producto | E8: MOD-01 | F8: APP-01 | G8: Must | H8: MVP | I8: TR-RNF-101, TR-RNF-027 | J8: TR-CA-013, TR-CA-014, TR-CA-015 | K8: TR-ORG, TR-SEG, TR-EVT | L8: plat.suscripcion.gestionar
A9: TR-P01 | B9: Alta y configuración de tenant | C9: TR-RF-006 | D9: Cambiar estado del tenant | E9: MOD-01 | F9: APP-01 | G9: Must | H9: MVP | I9: TR-RNF-021, TR-RNF-013 | J9: TR-CA-016, TR-CA-017, TR-CA-018 | K9: TR-ORG, TR-SEG, TR-AUD, TR-NOT | L9: plat.tenant.cambiar_estado
A10: TR-P01 | B10: Alta y configuración de tenant | C10: TR-RF-007 | D10: Controlar vencimiento de prueba y suscripción | E10: MOD-01 | F10: APP-03 | G10: Must | H10: MVP | I10: TR-RNF-005, TR-RNF-008 | J10: TR-CA-019, TR-CA-020, TR-CA-021 | K10: TR-ORG, TR-NOT, TR-CFG, TR-EVT | L10: plat.sistema.job
A11: TR-P01 | B11: Alta y configuración de tenant | C11: TR-RF-021 | D11: Transferir propiedad del tenant | E11: MOD-02 | F11: APP-02 | G11: Could | H11: R2 | I11: TR-RNF-009, TR-RNF-021 | J11: TR-CA-056, TR-CA-057 | K11: TR-SEG, TR-AUD, TR-NOT | L11: plat.tenant.transferir
A12: TR-P01 | B12: Alta y configuración de tenant | C12: TR-RF-047 | D12: Controlar cuota de consultas por plan | E12: MOD-07 | F12: APP-01 | G12: Must | H12: MVP | I12: TR-RNF-128, TR-RNF-007 | J12: TR-CA-120, TR-CA-121, TR-CA-122 | K12: TR-IDN, TR-NOT, TR-ORG | L12: plat.identidad.cuota
A13: TR-P01 | B13: Alta y configuración de tenant | C13: TR-RF-052 | D13: Configurar emisor electrónico | E13: MOD-08 | F13: APP-02 | G13: Must | H13: MVP | I13: TR-RNF-113, TR-RNF-017 | J13: TR-CA-133, TR-CA-134, TR-CA-135 | K13: TR-FE, TR-ARC, TR-AUD, TR-NOT | L13: plat.fe.configurar
A14: TR-P01 | B14: Alta y configuración de tenant | C14: TR-RF-073 | D14: Facturar y cobrar la suscripción del tenant | E14: MOD-09 | F14: APP-01 | G14: Must | H14: R2 | I14: TR-RNF-104, TR-RNF-128 | J14: TR-CA-182, TR-CA-183 | K14: TR-PAG, TR-FE, TR-ORG, TR-NOT | L14: plat.facturacion.gestionar
... A195: TR-P13 | B195: Reportes y analítica | C195: TR-RF-105 | D195: Orquestar agente conversacional con confirmación | E195: MOD-15 | F195: APP-03 | G195: Should | H195: R2 | I195: TR-RNF-115, TR-RNF-030, TR-RNF-007 | J195: TR-CA-256, TR-CA-257, TR-CA-258 | K195: TR-IA, TR-NOT, TR-PAG, TR-AUD | L195: plat.ia.agente

Sheet Componentes
A1: Matriz de componentes transversales y núcleos
A2: Uso declarado por el sistema y módulos que lo utilizan (● = algún RF del módulo usa el componente).
A3: Código | B3: Componente | C3: Uso | D3: Interfaz | E3: Detalle | F3: N.° RF | G3: MOD-01 | H3: MOD-02 | I3: MOD-03 | J3: MOD-04 | K3: MOD-05 | L3: MOD-06 | M3: MOD-07 | N3: MOD-08 | O3: MOD-09 | P3: MOD-10 | Q3: MOD-11 | R3: MOD-12 | S3: MOD-13 | T3: MOD-14 | U3: MOD-15 | V3: MOD-16 | W3: MOD-17 | X3: MOD-18 | Y3: MOD-19 | Z3: MOD-20 | AA3: MOD-21
A4: TR-ORG | B4: Organización y suscripciones | C4: Provee | D4: API interna | E4: API org: tenants, empresas, sucursales, unidades, suscripciones (/v1/org/*); OrgContextService (tenant/empresa/sucursal del request); eventos tenant.creado, empresa.creada, sucursal.creada, suscripcion.cambiada, suscripcion.vencida, tenant.suspendido | F4: =SUMPRODUCT(--ISNUMBER(SEARCH(A4,RF!$P$4:$P$141))) -> 22 | G4: ● | H4: ● | K4: ● | L4: ● | M4: ● | O4: ● | U4: ● | W4: ● | X4: ● | AA4: ●
A5: TR-SEG | B5: Seguridad | C5: Provee | D5: API interna | E5: Guard @RequierePermiso y PermisoService (seg.permisos_efectivos, menu_usuario, sucursales_accesibles); API de usuarios, membresías, roles, perfiles y asignaciones; aplicación de manifiestos; step-up MFA; acceso de soporte; librería Angular seguridad-cliente | F5: =SUMPRODUCT(--ISNUMBER(SEARCH(A5,RF!$P$4:$P$141))) -> 32 | G5: ● | H5: ● | J5: ● | N5: ● | O5: ● | Q5: ● | R5: ● | S5: ● | T5: ● | Y5: ● | Z5: ● | AA5: ●
A6: TR-CAT | B6: Catálogos, enumerados y tablas maestras | C6: Provee | D6: API interna | E6: GET /v1/catalogos/{codigo}/items con ETag; CatalogoPort.validarItem; CalendarioPort.sumarDiasHabiles; importación de tablas oficiales; evento catalogo.actualizado; componente <ui-catalogo-select> | F6: =SUMPRODUCT(--ISNUMBER(SEARCH(A6,RF!$P$4:$P$141))) -> 20 | G6: ● | I6: ● | L6: ● | N6: ● | R6: ● | X6: ● | AA6: ●
A7: TR-CFG | B7: Parámetros jerárquicos | C7: Provee | D7: API interna | E7: ParametroPort.valor(codigo, contexto) con origen; API de valores por alcance e historial; evento parametro.cambiado | F7: =SUMPRODUCT(--ISNUMBER(SEARCH(A7,RF!$P$4:$P$141))) -> 13 | G7: ● | H7: ● | I7: ● | J7: ● | N7: ● | U7: ● | W7: ● | AA7: ●
A8: TR-SEQ | B8: Correlativos y series | C8: Provee | D8: API interna | E8: CorrelativoPort.siguiente(empresa, tipo, serie) transaccional; API de series; reserva de bloques offline para el agente local | F8: =SUMPRODUCT(--ISNUMBER(SEARCH(A8,RF!$P$4:$P$141))) -> 11 | G8: ● | K8: ● | N8: ● | R8: ● | AA8: ●
A9: TR-PER | B9: Personas | C9: Provee | D9: API interna | E9: PersonaPort (buscar, registrar, asignarRol, consentimientos); eventos persona.registrada, persona.actualizada, persona.fusionada, consentimiento.revocado; componente <ui-persona-buscador> | F9: =SUMPRODUCT(--ISNUMBER(SEARCH(A9,RF!$P$4:$P$141))) -> 15 | L9: ● | M9: ● | P9: ● | R9: ● | X9: ● | Y9: ●
A10: TR-IDN | B10: Identidad e interoperabilidad | C10: Provee | D10: API interna | E10: IdentidadPort.validar/consultar(tipo, numero, motivo) con caché y cuota; API de identidad portable (solicitar, confirmar, datos autorizados, revocar) | F10: =SUMPRODUCT(--ISNUMBER(SEARCH(A10,RF!$P$4:$P$141))) -> 12 | G10: ● | L10: ● | M10: ● | N10: ●
A11: TR-FE | B11: Facturación electrónica | C11: Provee | D11: API interna | E11: ComprobantePort.emitir (01, 03, 07, 08), resumen diario, baja, PDF/ticket, consulta pública; workers de envío y contingencia; eventos cpe.emitido, cpe.aceptado, cpe.rechazado, cpe.nota_emitida | F11: =SUMPRODUCT(--ISNUMBER(SEARCH(A11,RF!$P$4:$P$141))) -> 16 | N11: ● | O11: ● | Y11: ● | AA11: ●
A12: TR-PAG | B12: Pagos | C12: Provee | D12: Webhook | E12: PagoPort (intención, Yape/Plin, link, reembolso, recurrente); POST /v1/pagos/webhooks/{pasarela}; conciliación; eventos pago.confirmado, pago.fallido, reembolso.confirmado, cobro_recurrente.fallido; componente <ui-checkout> | F12: =SUMPRODUCT(--ISNUMBER(SEARCH(A12,RF!$P$4:$P$141))) -> 10 | O12: ● | U12: ●
A13: TR-NOT | B13: Notificaciones | C13: Provee | D13: API interna | E13: NotificacionPort.enviar/programar/cancelar; plantillas por canal; preferencias y bajas; callbacks de estado de proveedores; centro de notificaciones Socket.IO | F13: =SUMPRODUCT(--ISNUMBER(SEARCH(A13,RF!$P$4:$P$141))) -> 37 | G13: ● | H13: ● | M13: ● | N13: ● | O13: ● | P13: ● | R13: ● | T13: ● | U13: ● | V13: ● | W13: ● | X13: ● | Y13: ● | Z13: ●
A14: TR-ARC | B14: Archivos | C14: Provee | D14: API interna | E14: ArchivoPort (URL firmada de carga, versión, URL firmada de descarga, retención); evento archivo.disponible; componente <ui-archivo-carga> | F14: =SUMPRODUCT(--ISNUMBER(SEARCH(A14,RF!$P$4:$P$141))) -> 23 | I14: ● | L14: ● | N14: ● | O14: ● | Q14: ● | R14: ● | T14: ● | U14: ● | W14: ● | X14: ●
A15: TR-AUD | B15: Auditoría | C15: Provee | D15: API interna | E15: Interceptor @Auditable y AuditoriaPort (registrar, registrarAccesoSensible); visor y exportación; verificación de integridad; API ARCO e incidentes; eventos arco.solicitado, persona.cancelacion_aprobada | F15: =SUMPRODUCT(--ISNUMBER(SEARCH(A15,RF!$P$4:$P$141))) -> 46 | G15: ● | H15: ● | I15: ● | J15: ● | K15: ● | L15: ● | M15: ● | N15: ● | O15: ● | Q15: ● | R15: ● | S15: ● | T15: ● | U15: ● | Y15: ● | Z15: ●
A16: TR-EVT | B16: Eventos de dominio | C16: Provee | D16: Evento | E16: EventoPort.publicar (outbox transaccional), decorador @SuscribirEvento, registro de esquemas, despachador BullMQ, cola de fallidos y reproceso; sync.read_events | F16: =SUMPRODUCT(--ISNUMBER(SEARCH(A16,RF!$P$4:$P$141))) -> 38 | G16: ● | H16: ● | I16: ● | J16: ● | L16: ● | N16: ● | O16: ● | Q16: ● | R16: ● | S16: ● | V16: ● | X16: ● | Y16: ● | Z16: ● | AA16: ●
A17: TR-REP | B17: Reportes y tableros | C17: Provee | D17: API interna | E17: Motor de reportes declarados en manifiesto (ejecutar, exportar XLSX/PDF/CSV, programar); tableros por rol | F17: =SUMPRODUCT(--ISNUMBER(SEARCH(A17,RF!$P$4:$P$141))) -> 10 | H17: ● | N17: ● | O17: ● | R17: ● | T17: ●
A18: TR-IA | B18: Servicios de IA | C18: Provee | D18: API interna | E18: IaPort por caso de uso vía pasarela de modelos; enmascaramiento de datos personales; extracción documental; RAG por tenant; orquestador de agentes; medición de consumo | F18: =SUMPRODUCT(--ISNUMBER(SEARCH(A18,RF!$P$4:$P$141))) -> 7 | U18: ● | W18: ●
A19: TR-OBS | B19: Observabilidad | C19: Provee | D19: Vista SQL | E19: Registro de indicadores por minuto desde eventos (obs.registrar); reglas y evaluación de alertas; vista obs.v_salud_sucursal; trazas OpenTelemetry | F19: =SUMPRODUCT(--ISNUMBER(SEARCH(A19,RF!$P$4:$P$141))) -> 18 | H19: ● | N19: ● | P19: ● | R19: ● | S19: ● | T19: ● | U19: ● | V19: ● | W19: ● | Z19: ● | AA19: ●
A20: TR-SOP | B20: Centro de soporte | C20: Provee | D20: Librería Angular | E20: API de tickets (sop.crear_ticket, cambiar_estado, crear_desde_alerta, resolver_problema); vistas v_evento_cliente y v_tablero_sla; librería Angular soporte-widget | F20: =SUMPRODUCT(--ISNUMBER(SEARCH(A20,RF!$P$4:$P$141))) -> 13 | H20: ● | N20: ● | V20: ● | W20: ● | AA20: ●
A21: TR-CMS | B21: Gestor de contenidos web | C21: Provee | D21: Librería Angular | E21: Administración de sitio, páginas por bloques, menús, medios, noticias, SEO y formularios; renderizado SSR con caché CDN; evento cms.pagina_publicada | F21: =SUMPRODUCT(--ISNUMBER(SEARCH(A21,RF!$P$4:$P$141))) -> 6 | X21: ●
A22: TR-POR | B22: Portal del cliente final | C22: Provee | D22: Librería Angular | E22: Librería portal-shell: registro, OTP, perfil, consentimientos, mis transacciones (contribuciones por producto), mis autorizaciones | F22: =SUMPRODUCT(--ISNUMBER(SEARCH(A22,RF!$P$4:$P$141))) -> 10 | M22: ● | N22: ● | O22: ● | P22: ● | R22: ● | Y22: ●
A23: TR-INT | B23: Integración externa | C23: Provee | D23: Webhook | E23: API pública /v1 con OAuth2 client_credentials y límites por plan; webhooks salientes firmados; sincronización por cursor con conciliación; cliente GitHub para problemas | F23: =SUMPRODUCT(--ISNUMBER(SEARCH(A23,RF!$P$4:$P$141))) -> 5 | W23: ● | Z23: ●
A24: TR-EDGE | B24: Agente local (edge) | C24: Provee | D24: API interna | E24: Agente plataforma-edge: enrolamiento, impresión ESC/POS y cajón, cola offline cifrada, caché local, latido y actualización remota; canal Socket.IO con la nube | F24: =SUMPRODUCT(--ISNUMBER(SEARCH(A24,RF!$P$4:$P$141))) -> 8 | K24: ● | N24: ● | V24: ● | AA24: ●
A25: NU-POS | B25: Núcleo POS | E25: No utilizado por este sistema | F25: =SUMPRODUCT(--ISNUMBER(SEARCH(A25,RF!$P$4:$P$141))) -> 0
A26: NU-AGE | B26: Núcleo Agenda y Turnos | E26: No utilizado por este sistema | F26: =SUMPRODUCT(--ISNUMBER(SEARCH(A26,RF!$P$4:$P$141))) -> 0
A27: NU-DOC | B27: Núcleo documental | E27: No utilizado por este sistema | F27: =SUMPRODUCT(--ISNUMBER(SEARCH(A27,RF!$P$4:$P$141))) -> 0
A29: Leyenda de módulos
A30: MOD-01 | B30: Organización y suscripciones (TR-ORG)
A31: MOD-02 | B31: Seguridad y accesos (TR-SEG)
A32: MOD-03 | B32: Catálogos y tablas maestras (TR-CAT)
A33: MOD-04 | B33: Parámetros jerárquicos (TR-CFG)
A34: MOD-05 | B34: Correlativos y series (TR-SEQ)
A35: MOD-06 | B35: Personas (TR-PER)
A36: MOD-07 | B36: Identidad e interoperabilidad (TR-IDN)
A37: MOD-08 | B37: Facturación electrónica (TR-FE)
A38: MOD-09 | B38: Pagos y conciliación (TR-PAG)
A39: MOD-10 | B39: Notificaciones (TR-NOT)
A40: MOD-11 | B40: Archivos (TR-ARC)
A41: MOD-12 | B41: Auditoría y datos personales (TR-AUD)
... A50: MOD-21 | B50: Agente local (TR-EDGE)

Sheet Consumidores
A1: Matriz componente × sistema consumidor
A2: Uso declarado por cada sistema en su especificación (C = consume, I = integra, E = extiende, P = publica eventos).
A3: Código | B3: Componente | C3: REST | D3: PSI | E3: COL | F3: LIB | G3: GYM | H3: CLI | I3: DOC | J3: ECO | K3: LEX | L3: N.° sistemas | M3: Forma de integración
A4: TR-ORG | B4: Organización y suscripciones | C4: C | D4: C | E4: C | F4: C | G4: C | H4: C | I4: C | J4: C | K4: C | L4: =COUNTIF(C4:K4,"?") -> 9 | M4: Módulo NestJS OrgModule (contexto tenant/empresa/sucursal en cada request) + rutas de administración embebidas en <cod>-backoffice
A5: TR-SEG | B5: Seguridad | C5: I | D5: C | E5: C | F5: C | G5: C | H5: E | I5: I | J5: E | K5: C | L5: =COUNTIF(C5:K5,"?") -> 9 | M5: Guard NestJS @RequierePermiso('producto.recurso.accion') + librería Angular seguridad-cliente (OIDC, menú por permisos, directiva *siPermiso)
A6: TR-CAT | B6: Catálogos, enumerados y tablas maestras | C6: C | D6: C | E6: C | F6: C | G6: C | H6: C | I6: C | J6: C | K6: E | L6: =COUNTIF(C6:K6,"?") -> 9 | M6: API GET /v1/catalogos/{codigo}/items con ETag + puerto CatalogoPort.validarItem() + componente Angular <ui-catalogo-select>
A7: TR-CFG | B7: Parámetros jerárquicos | C7: C | D7: C | E7: C | F7: C | G7: C | H7: C | I7: C | J7: C | K7: C | L7: =COUNTIF(C7:K7,"?") -> 9 | M7: Puerto ParametroPort.valor(codigo, contexto) con caché Redis; parámetros declarados en el manifiesto del producto
A8: TR-SEQ | B8: Correlativos y series | C8: C | D8: C | E8: C | F8: C | G8: C | H8: C | I8: C | J8: C | K8: C | L8: =COUNTIF(C8:K8,"?") -> 9 | M8: Puerto CorrelativoPort.siguiente(empresa, tipo, serie) dentro de la transacción del producto (comprobantes, tickets, expedientes, historias, kardex)
A9: TR-PER | B9: Personas | C9: C | D9: E | E9: C | F9: C | G9: E | H9: E | I9: I | J9: C | K9: C | L9: =COUNTIF(C9:K9,"?") -> 9 | M9: Puerto PersonaPort (buscar, registrar, asignar rol de persona) + componente Angular <ui-persona-buscador>; cada producto guarda solo persona_id
A10: TR-IDN | B10: Identidad e interoperabilidad | C10: C | D10: C | E10: C | F10: C | G10: C | H10: C | I10: C | J10: C | K10: I | L10: =COUNTIF(C10:K10,"?") -> 9 | M10: Puerto IdentidadPort.consultar(tipo, numero, motivo) invocado al registrar personas o emitir comprobantes; nivel 3 en PSI, CLI, GYM y LEX
A11: TR-FE | B11: Facturación electrónica | C11: I | D11: I | F11: I | G11: C | H11: I | J11: C | K11: I | L11: =COUNTIF(C11:K11,"?") -> 7 | M11: Puerto ComprobantePort.emitir() y eventos cpe.aceptado / cpe.rechazado; consulta pública de comprobantes en <cod>-web
A12: TR-PAG | B12: Pagos | C12: I | D12: I | F12: I | G12: I | H12: I | I12: I | J12: I | K12: I | L12: =COUNTIF(C12:K12,"?") -> 8 | M12: Puerto PagoPort (intención, link, reembolso, recurrencia) y eventos pago.confirmado / pago.fallido; componente Angular <ui-checkout>
A13: TR-NOT | B13: Notificaciones | C13: C | D13: I | E13: C | F13: C | G13: C | H13: C | I13: C | J13: C | K13: C | L13: =COUNTIF(C13:K13,"?") -> 9 | M13: Puerto NotificacionPort.enviar/programar con plantillas por código; centro de notificaciones en el shell de backoffice y del portal
A14: TR-ARC | B14: Archivos | C14: C | D14: C | E14: C | F14: C | G14: C | H14: C | I14: C | J14: C | K14: C | L14: =COUNTIF(C14:K14,"?") -> 9 | M14: Puerto ArchivoPort (subir, versionar, url firmada) + componente Angular <ui-archivo-carga>
A15: TR-AUD | B15: Auditoría | C15: P | D15: P | E15: P | F15: P | G15: P | H15: C | I15: P | J15: P | K15: C | L15: =COUNTIF(C15:K15,"?") -> 9 | M15: Interceptor NestJS @Auditable y puerto AuditoriaPort.registrarAccesoSensible(); visor de auditoría embebido en el backoffice
A16: TR-EVT | B16: Eventos de dominio | C16: P | D16: P | E16: P | F16: P | G16: P | H16: P | I16: P | J16: P | K16: P | L16: =COUNTIF(C16:K16,"?") -> 9 | M16: Puerto EventoPort.publicar() en la misma transacción (outbox) y decorador @SuscribirEvento para consumidores idempotentes
A17: TR-REP | B17: Reportes y tableros | C17: C | D17: C | E17: E | F17: C | G17: C | H17: C | I17: C | J17: C | K17: C | L17: =COUNTIF(C17:K17,"?") -> 9 | M17: Reportes declarados en el manifiesto del producto (consulta parametrizada + permiso) ejecutados por el motor común; tableros por rol
A18: TR-IA | B18: Servicios de IA | C18: C | D18: C | E18: C | F18: C | G18: C | H18: C | I18: C | J18: C | K18: C | L18: =COUNTIF(C18:K18,"?") -> 9 | M18: Puerto IaPort por caso de uso (extraer, clasificar, resumir, responder, predecir) vía pasarela de modelos; copiloto analítico en todos y agente conversacional en REST PSI COL GYM CLI DOC ECO LEX
A19: TR-OBS | B19: Observabilidad | C19: I | D19: C | E19: C | F19: C | G19: C | H19: C | I19: I | J19: C | K19: C | L19: =COUNTIF(C19:K19,"?") -> 9 | M19: Indicadores de negocio declarados en el manifiesto y alimentados por eventos; trazas OpenTelemetry automáticas en la API
A20: TR-SOP | B20: Centro de soporte | E20: C | L20: =COUNTIF(C20:K20,"?") -> 1 | M20: Widget Angular soporte-widget en el shell de backoffice (crea tickets con contexto) y tickets automáticos desde alertas
A21: TR-CMS | B21: Gestor de contenidos web | C21: E | D21: E | E21: E | F21: C | G21: E | H21: E | I21: E | J21: E | K21: E | L21: =COUNTIF(C21:K21,"?") -> 9 | M21: Administración del sitio en plataforma-admin-cliente y renderizado SSR de páginas por bloques en <cod>-web
A22: TR-POR | B22: Portal del cliente final | C22: C | D22: E | E22: C | F22: C | G22: E | H22: E | I22: E | J22: E | K22: E | L22: =COUNTIF(C22:K22,"?") -> 9 | M22: Librería portal-shell montada en <cod>-web: registro, acceso OTP, perfil, consentimientos; cada producto aporta sus vistas (mis citas, mis pedidos, mis trámites)
A23: TR-INT | B23: Integración externa | D23: I | E23: I | F23: I | G23: C | H23: P | I23: P | J23: P | K23: I | L23: =COUNTIF(C23:K23,"?") -> 8 | M23: API pública /v1 por producto con clientes OAuth2 y webhooks salientes; sincronización por cursor con bases institucionales en COL y DOC
A24: TR-EDGE | B24: Agente local (edge) | C24: I | E24: E | F24: I | G24: E | H24: I | K24: I | L24: =COUNTIF(C24:K24,"?") -> 6 | M24: Agente local plataforma-edge con plugins por producto: impresión de comandas y tickets, cola offline, kiosco y pantallas de llamado, control de acceso
A25: NU-POS | B25: Núcleo POS | C25: E | F25: E | G25: C | H25: E | J25: C | K25: C | L25: =COUNTIF(C25:K25,"?") -> 6
A26: NU-AGE | B26: Núcleo Agenda y Turnos | C26: C | D26: E | E26: E | G26: C | H26: E | I26: I | K26: C | L26: =COUNTIF(C26:K26,"?") -> 7
A27: NU-DOC | B27: Núcleo documental | D27: C | E27: I | H27: C | I27: E | K27: E | L27: =COUNTIF(C27:K27,"?") -> 5
